Workbook

Sheet Invoices
A1: Date of submission | B1: Dealer Name | C1: Dealer Code | D1: SAP# | E1: Invoice # | F1: Work description | H1: Work Category | I1: Labor | J1: Misc | K1: Parts | L1: Less Insurance | M1: Net for SAP | N1: GST | O1: PST | P1: Total Tax | Q1: tax type | R1: total | S1: Vehicle | T1: 5VIN
A2: 46084 | B2: Westminster Toyota | C2: 1117 | D2: 3600270655 | E2: 10941 | F2: GST portion for repairs | H2: =+VLOOKUP(F2,Categories!A:B,2,) -> Financial / Admin | I2: 1915.95 | J2: 0 | K2: 0 | L2: 0 | M2: =+I2+J2+K2-L2 -> 1915.95 | N2: 0 | O2: 0 | P2: =+N2+O2 -> 0 | Q2: NO TAX | R2: =+ROUND(P2+M2,2) -> 1915.95 | S2: bZ | T2: 27683
A3: 46084 | B3: OpenRoad Toyota Richmond | C3: 1078 | D3: 3600270100 | E3: 361743 | F3: Wheel cover replacement | H3: =+VLOOKUP(F3,Categories!A:B,2,) -> Tires & Wheels | I3: 0 | J3: 0 | K3: 116.62 | L3: 0 | M3: =+I3+J3+K3-L3 -> 116.62 | N3: 5.83 | O3: 8.16 | P3: =+N3+O3 -> 13.99 | Q3: GST + PST | R3: =+ROUND(P3+M3,2) -> 130.61 | S3: bZ | T3: 44818
A4: 46085 | B4: Destination Toyota Burnaby | C4: 1122 | D4: 3600270660 | E4: 694999 | F4: Brakes repair | H4: Repair | I4: 694.95 | J4: 0 | K4: 0 | L4: 0 | M4: =+I4+J4+K4-L4 -> 694.95 | N4: 34.75 | O4: 48.65 | P4: =+N4+O4 -> 83.4 | Q4: GST + PST | R4: =+ROUND(P4+M4,2) -> 778.35 | S4: bZ | T4: 50148
A5: 46085 | B5: Destination Toyota Burnaby | C5: 1122 | D5: 3600270660 | E5: 378998 | F5: Body shop | H5: Repair | I5: 554.65 | J5: =194+112.69 -> 306.69 | K5: 1631.4 | L5: 0 | M5: =+I5+J5+K5-L5 -> 2492.74 | N5: 124.64 | O5: 174.49 | P5: =+N5+O5 -> 299.13 | Q5: No TAX | R5: =+ROUND(P5+M5,2) -> 2791.87 | S5: bZ | T5: 50148
A6: 46091 | B6: OpenRoad Toyota Richmond | C6: 1078 | D6: 3600270750 | E6: 349353 | F6: Rim repair & alignment | H6: =+VLOOKUP(F6,Categories!A:B,2,) -> Tires & Wheels | I6: 189.9 | J6: 350 | K6: 121.1 | L6: 0 | M6: =+I6+J6+K6-L6 -> 661 | N6: 33.06 | O6: 0 | P6: =+N6+O6 -> 33.06 | Q6: =+IF(AND(N6>0,O6=0),"GST ONLY",IF(AND(N6>0,#REF!>=0),"GST + PST","NO TAX")) -> GST ONLY | R6: =+ROUND(P6+M6,2) -> 694.06 | S6: bZ | T6: 49744
A7: 46091 | B7: OpenRoad Toyota Richmond | C7: 1078 | D7: 3600270750 | E7: 335824 | F7: Window Bezel Replacement | H7: Repair | I7: 51.59 | J7: 0 | K7: 155.85 | L7: 0 | M7: =+I7+J7+K7-L7 -> 207.44 | N7: 10.37 | O7: 0 | P7: =+N7+O7 -> 10.37 | Q7: =+IF(AND(N7>0,O7=0),"GST ONLY",IF(AND(N7>0,#REF!>=0),"GST + PST","NO TAX")) -> GST ONLY | R7: =+ROUND(P7+M7,2) -> 217.81 | S7: bZ | T7: 94733
A8: 46091 | B8: OpenRoad Toyota Richmond | C8: 1078 | D8: 3600270750 | E8: 348815 | F8: Hydrogen refuel | H8: =+VLOOKUP(F8,Categories!A:B,2,) -> Fuel & Recharge | I8: 25 | J8: =57.3+2.72 -> 60.02 | K8: 0 | L8: 0 | M8: =+I8+J8+K8-L8 -> 85.02 | N8: 4.26 | O8: 0 | P8: =+N8+O8 -> 4.26 | Q8: =+IF(AND(N8>0,O8=0),"GST ONLY",IF(AND(N8>0,#REF!>=0),"GST + PST","NO TAX")) -> GST ONLY | R8: =+ROUND(P8+M8,2) -> 89.28 | S8: Mirai | T8: 11764
A9: 46091 | B9: Westminster Toyota | C9: 1117 | D9: 3600270769 | E9: 390687 | F9: Windshield replacement | H9: Repair | I9: 0 | J9: 0 | K9: 1496.67 | L9: 0 | M9: =+I9+J9+K9-L9 -> 1496.67 | N9: 74.83 | O9: 104.77 | P9: =+N9+O9 -> 179.6 | Q9: =+IFERROR(+IF(AND(N9>0,O9=0),"GST ONLY",IF(AND(N9>0,O9>=0),"GST + PST","NO TAX")),"") -> GST + PST | R9: =+ROUND(P9+M9,2) -> 1676.27 | S9: bZ | T9: 50229
A10: 46093 | B10: Destination Toyota Burnaby | C10: 1122 | D10: 3600270795 | E10: 378347 | F10: deductible portion plus GST | H10: =+VLOOKUP(F10,Categories!A:B,2,) -> Financial / Admin | I10: 0 | J10: 2500 | K10: 0 | L10: 0 | M10: =+I10+J10+K10-L10 -> 2500 | N10: 326.27 | O10: 0 | P10: =+N10+O10 -> 326.27 | Q10: =+IFERROR(+IF(AND(N10>0,O10=0),"GST ONLY",IF(AND(N10>0,O10>=0),"GST + PST","NO TAX")),"") -> GST ONLY | R10: =+ROUND(P10+M10,2) -> 2826.27 | S10: bZ | T10: 51242
A11: 46093 | B11: Destination Toyota Burnaby | C11: 1122 | D11: 3600270795 | E11: 627377 | F11: Hubcap replacement | H11: =+VLOOKUP(F11,Categories!A:B,2,) -> Tires & Wheels | I11: 0 | J11: 0 | K11: 109.82 | L11: 0 | M11: =+I11+J11+K11-L11 -> 109.82 | N11: 5.49 | O11: 7.69 | P11: =+N11+O11 -> 13.18 | Q11: =+IFERROR(+IF(AND(N11>0,O11=0),"GST ONLY",IF(AND(N11>0,O11>=0),"GST + PST","NO TAX")),"") -> GST + PST | R11: =+ROUND(P11+M11,2) -> 123 | S11: bZ | T11: 51242
A12: 46093 | B12: Destination Toyota Burnaby | C12: 1122 | D12: 3600270795 | E12: 688702 | F12: Bronze cleaning | H12: =+VLOOKUP(F12,Categories!A:B,2,) -> Cleaning | I12: 0 | J12: 130 | K12: 0 | L12: 0 | M12: =+I12+J12+K12-L12 -> 130 | N12: =+M12*0.05 -> 6.5 | O12: =+M12*0.07 -> 9.1 | P12: =+N12+O12 -> 15.6 | Q12: =+IFERROR(+IF(AND(N12>0,O12=0),"GST ONLY",IF(AND(N12>0,O12>=0),"GST + PST","NO TAX")),"") -> GST + PST | R12: =+ROUND(P12+M12,2) -> 145.6 | S12: bZ | T12: 50388
A13: 46093 | B13: Destination Toyota Burnaby | C13: 1122 | D13: 3600270795 | E13: 688702 | F13: Recharge | H13: =+VLOOKUP(F13,Categories!A:B,2,) -> Fuel & Recharge | I13: 0 | J13: 45 | K13: 0 | L13: 0 | M13: =+I13+J13+K13-L13 -> 45 | N13: =+M13*0.05 -> 2.25 | O13: =+M13*0.07 -> 3.15 | P13: =+N13+O13 -> 5.4 | Q13: =+IFERROR(+IF(AND(N13>0,O13=0),"GST ONLY",IF(AND(N13>0,O13>=0),"GST + PST","NO TAX")),"") -> GST + PST | R13: =+ROUND(P13+M13,2) -> 50.4 | S13: bZ | T13: 50388
A14: 46093 | B14: Destination Toyota Burnaby | C14: 1122 | D14: 3600270795 | E14: 690816 | F14: Tire replacement | H14: =+VLOOKUP(F14,Categories!A:B,2,) -> Tires & Wheels | I14: 40 | J14: 6.5 | K14: 408.77 | L14: 0 | M14: =+I14+J14+K14-L14 -> 455.27 | N14: 22.76 | O14: 31.87 | P14: =+N14+O14 -> 54.63 | Q14: =+IFERROR(+IF(AND(N14>0,O14=0),"GST ONLY",IF(AND(N14>0,O14>=0),"GST + PST","NO TAX")),"") -> GST + PST | R14: =+ROUND(P14+M14,2) -> 509.9 | S14: bZ | T14: 50706
A15: 46093 | B15: Destination Toyota Burnaby | C15: 1122 | D15: 3600270795 | E15: 699272 | F15: Cable replacement | H15: Repair | I15: 0 | J15: 75 | K15: 0 | L15: 0 | M15: =+I15+J15+K15-L15 -> 75 | N15: 0 | O15: 0 | P15: =+N15+O15 -> 0 | Q15: =+IFERROR(+IF(AND(N15>0,O15=0),"GST ONLY",IF(AND(N15>0,O15>=0),"GST + PST","NO TAX")),"") -> NO TAX | R15: =+ROUND(P15+M15,2) -> 75 | S15: bZ | T15: 50706
A16: 46093 | B16: Destination Toyota Burnaby | C16: 1122 | D16: 3600270795 | E16: 701767 | F16: Tire replacement | H16: =+VLOOKUP(F16,Categories!A:B,2,) -> Tires & Wheels | I16: 35 | J16: 6.5 | K16: 443.09 | L16: 0 | M16: =+I16+J16+K16-L16 -> 484.59 | N16: 24.23 | O16: 33.92 | P16: =+N16+O16 -> 58.15 | Q16: =+IFERROR(+IF(AND(N16>0,O16=0),"GST ONLY",IF(AND(N16>0,O16>=0),"GST + PST","NO TAX")),"") -> GST + PST | R16: =+ROUND(P16+M16,2) -> 542.74 | S16: bZ | T16: 51361
A17: 46093 | B17: Destination Toyota Burnaby | C17: 1122 | D17: 3600270796 | E17: 694734 | F17: CVI | H17: =+VLOOKUP(F17,Categories!A:B,2,) -> Inspection (CVI) | I17: 209.95 | J17: 0 | K17: 0 | L17: 0 | M17: 209.95 | N17: 10.5 | O17: 14.7 | P17: 25.2 | Q17: GST + PST | R17: 235.15 | S17: bZ | T17: 50104
A18: 46098 | B18: Destination Toyota Burnaby | C18: 1122 | D18: 3600270822 | E18: 704619 | F18: Recharge | H18: =+VLOOKUP(F18,Categories!A:B,2,) -> Fuel & Recharge | I18: 0 | J18: 25 | K18: 0 | L18: 0 | M18: 25 | N18: 0 | O18: 0 | P18: 0 | Q18: NO TAX | R18: 25 | S18: bZ | T18: 51104
A19: 46106 | B19: Jim Pattison Toyota Surrey | C19: 1088 | D19: 3600271656 | E19: 541976 | F19: Wiper replacement | H19: Repair | I19: 17 | J19: 0 | K19: 30 | L19: 0 | M19: 47 | N19: 2.35 | O19: 3.29 | P19: 5.64 | Q19: GST + PST | R19: 52.64 | S19: bZ | T19: 58289
A20: 46106 | B20: Destination Toyota Burnaby | C20: 1122 | D20: 3600271657 | E20: 704724 | F20: CVI | H20: =+VLOOKUP(F20,Categories!A:B,2,) -> Inspection (CVI) | I20: 209.95 | J20: 3.5 | K20: 0 | L20: 0 | M20: =+I20+J20+K20-L20 -> 213.45 | N20: =+M20*0.05 -> 10.6725 | O20: =+M20*0.07 -> 14.9415 | P20: =+N20+O20 -> 25.614 | Q20: =+IFERROR(+IF(AND(N20>0,O20=0),"GST ONLY",IF(AND(N20>0,O20>=0),"GST + PST","NO TAX")),"") -> GST + PST | R20: =+ROUND(P20+M20,2) -> 239.06 | S20: bZ | T20: 94807
A21: 46106 | B21: Destination Toyota Burnaby | C21: 1122 | D21: 3600271657 | E21: 704724 | F21: Rotors service | H21: Repair | I21: =291+388 -> 679 | J21: 0 | K21: 0 | L21: 0 | M21: =+I21+J21+K21-L21 -> 679 | N21: =+M21*0.05 -> 33.95 | O21: =+M21*0.07 -> 47.53 | P21: =+N21+O21 -> 81.48 | Q21: =+IFERROR(+IF(AND(N21>0,O21=0),"GST ONLY",IF(AND(N21>0,O21>=0),"GST + PST","NO TAX")),"") -> GST + PST | R21: =+ROUND(P21+M21,2) -> 760.48 | S21: bZ | T21: 94807
A22: 46106 | B22: Destination Toyota Burnaby | C22: 1122 | D22: 3600271657 | E22: 704725 | F22: CVI | H22: =+VLOOKUP(F22,Categories!A:B,2,) -> Inspection (CVI) | I22: 209.95 | J22: 3.5 | K22: 0 | L22: 0 | M22: =+I22+J22+K22-L22 -> 213.45 | N22: =+M22*0.05 -> 10.6725 | O22: =+M22*0.07 -> 14.9415 | P22: =+N22+O22 -> 25.614 | Q22: =+IFERROR(+IF(AND(N22>0,O22=0),"GST ONLY",IF(AND(N22>0,O22>=0),"GST + PST","NO TAX")),"") -> GST + PST | R22: =+ROUND(P22+M22,2) -> 239.06 | S22: bZ | T22: 94917
A23: 46056 | B23: Destination Toyota Burnaby | C23: 1122 | D23: 3600268565 | E23: 699883 | F23: Recharge | H23: =+VLOOKUP(F23,Categories!A:B,2,) -> Fuel & Recharge | I23: 0 | J23: 25 | K23: 0 | L23: 0 | M23: 25 | N23: 0 | O23: 0 | P23: 0 | Q23: No TAX | R23: 25 | S23: bZ | T23: 94917
A24: 46056 | B24: Westminster Toyota | C24: 1117 | D24: 3600268566 | E24: 267242 | F24: Parts RO | H24: Repair | I24: 0 | J24: 0 | K24: 113.18 | L24: 0 | M24: 113.18 | N24: 5.66 | O24: 7.92 | P24: 13.58 | Q24: GST + PST | R24: 126.76 | S24: bZ | T24: 50463
A25: 46056 | B25: Westminster Toyota | C25: 1117 | D25: 3600268566 | E25: 380217 | F25: Mirai Fuel | H25: =+VLOOKUP(F25,Categories!A:B,2,) -> Fuel & Recharge | I25: 50.73 | J25: 6.09 | K25: 0 | L25: 0 | M25: 56.82 | N25: 2.84 | O25: 3.98 | P25: 6.82 | Q25: GST + PST | R25: 63.64 | S25: Mirai | T25: 08438
A26: 46056 | B26: Westminster Toyota | C26: 1117 | D26: 3600268566 | E26: 385688 | F26: Tire replacement | H26: =+VLOOKUP(F26,Categories!A:B,2,) -> Tires & Wheels | I26: 92.48 | J26: 24.1 | K26: 1097.96 | L26: 0 | M26: 1214.54 | N26: 60.73 | O26: 85.02 | P26: 145.75 | Q26: GST + PST | R26: 1360.29 | S26: bZ | T26: 50565
A27: 46065 | B27: Destination Toyota Burnaby | C27: 1122 | D27: 3600268722 | E27: 700700 | F27: Recharge | H27: =+VLOOKUP(F27,Categories!A:B,2,) -> Fuel & Recharge | I27: 0 | J27: 25 | K27: 0 | L27: 0 | M27: =+I27+J27+K27-L27 -> 25 | N27: 0 | O27: 0 | P27: =+N27+O27 -> 0 | Q27: No TAX | R27: =+ROUND(P27+M27,2) -> 25 | S27: bZ | T27: 51361
A28: 46065 | B28: Destination Toyota Burnaby | C28: 1122 | D28: 3600268722 | E28: 701262 | F28: Recharge | H28: =+VLOOKUP(F28,Categories!A:B,2,) -> Fuel & Recharge | I28: 0 | J28: 25 | K28: 0 | L28: 0 | M28: =+I28+J28+K28-L28 -> 25 | N28: 0 | O28: 0 | P28: =+N28+O28 -> 0 | Q28: No TAX | R28: =+ROUND(P28+M28,2) -> 25 | S28: bZ | T28: 50388
A29: 46072 | B29: Westminster Toyota | C29: 1117 | D29: 3600269377 | E29: 389772 | F29: Windshield Replacement | H29: Repair | I29: 0 | J29: 1496.67 | K29: 0 | L29: 0 | M29: =+I29+J29+K29-L29 -> 1496.67 | N29: 74.83 | O29: 104.77 | P29: =+N29+O29 -> 179.6 | Q29: No TAX | R29: =+ROUND(P29+M29,2) -> 1676.27 | S29: bZ | T29: 50340
A30: 46076 | B30: Destination Toyota Burnaby | C30: 1122 | D30: 3600269601 | E30: 702279 | F30: Recharge | H30: =+VLOOKUP(F30,Categories!A:B,2,) -> Fuel & Recharge | I30: 0 | J30: 25 | K30: 0 | L30: 0 | M30: =+I30+J30+K30-L30 -> 25 | N30: 0 | O30: 0 | P30: =+N30+O30 -> 0 | Q30: No TAX | R30: =+ROUND(P30+M30,2) -> 25 | S30: bZ | T30: 50716
A31: 46077 | B31: Westminster Toyota | C31: 1117 | D31: 10021143 | E31: 10674 | F31: Repair GST payable | H31: =+VLOOKUP(F31,Categories!A:B,2,) -> Financial / Admin | I31: 0 | J31: 0 | K31: 0 | L31: 0 | M31: =+I31+J31+K31-L31 -> 0 | N31: 505.96 | O31: 0 | P31: =+N31+O31 -> 505.96 | Q31: GST only | R31: =+ROUND(P31+M31,2) -> 505.96 | S31: bZ | T31: 27683
A32: 46077 | B32: Westminster Toyota | C32: 1117 | D32: 10021143 | E32: 10675 | F32: Repair GST payable | H32: =+VLOOKUP(F32,Categories!A:B,2,) -> Financial / Admin | I32: 0 | J32: 0 | K32: 0 | L32: 0 | M32: =+I32+J32+K32-L32 -> 0 | N32: 293.44 | O32: 0 | P32: =+N32+O32 -> 293.44 | Q32: GST only | R32: =+ROUND(P32+M32,2) -> 293.44 | S32: bZ | T32: 50006
A33: 46077 | B33: Westminster Toyota | C33: 1117 | D33: 10021143 | E33: 10685 | F33: Repair GST payable | H33: =+VLOOKUP(F33,Categories!A:B,2,) -> Financial / Admin | I33: 0 | J33: 0 | K33: 0 | L33: 0 | M33: =+I33+J33+K33-L33 -> 0 | N33: 124.44 | O33: 0 | P33: =+N33+O33 -> 124.44 | Q33: GST only | R33: =+ROUND(P33+M33,2) -> 124.44 | S33: bZ | T33: 58341
A34: 46035 | B34: OpenRoad Toyota Richmond | C34: 1078 | D34: 3600266854 | E34: 356803 | F34: Tire replacement | H34: =+VLOOKUP(F34,Categories!A:B,2,) -> Tires & Wheels | I34: 120.37 | J34: 6.5 | K34: 413.09 | L34: 0 | M34: =+I34+J34+K34-L34 -> 539.96 | N34: 27 | O34: 0 | P34: =+N34+O34 -> 27 | Q34: GST only | R34: =+ROUND(P34+M34,2) -> 566.96 | S34: bZ | T34: 94817
A35: 46035 | B35: Destination Toyota Burnaby | C35: 1122 | D35: 3600266904 | E35: 696665 | F35: CVI | H35: =+VLOOKUP(F35,Categories!A:B,2,) -> Inspection (CVI) | I35: 669.95 | J35: 0 | K35: 0 | L35: 0 | M35: =+I35+J35+K35-L35 -> 669.95 | N35: 33.5 | O35: 46.9 | P35: =+N35+O35 -> 80.4 | Q35: GST + PST | R35: =+ROUND(P35+M35,2) -> 750.35 | S35: bZ | T35: 51361
A36: 46035 | B36: Destination Toyota Burnaby | C36: 1122 | D36: 3600266904 | E36: 696911 | F36: CVI | H36: =+VLOOKUP(F36,Categories!A:B,2,) -> Inspection (CVI) | I36: 485.95 | J36: 0 | K36: 0 | L36: 0 | M36: =+I36+J36+K36-L36 -> 485.95 | N36: 24.3 | O36: 34.02 | P36: =+N36+O36 -> 58.32 | Q36: GST + PST | R36: =+ROUND(P36+M36,2) -> 544.27 | S36: bZ | T36: 51224
A37: 46035 | B37: Destination Toyota Burnaby | C37: 1122 | D37: 3600266904 | E37: 697579 | F37: CVI | H37: =+VLOOKUP(F37,Categories!A:B,2,) -> Inspection (CVI) | I37: 694.95 | J37: 0 | K37: 0 | L37: 0 | M37: =+I37+J37+K37-L37 -> 694.95 | N37: 34.75 | O37: 48.65 | P37: =+N37+O37 -> 83.4 | Q37: GST + PST | R37: =+ROUND(P37+M37,2) -> 778.35 | S37: bZ | T37: 51104
A38: 46035 | B38: Destination Toyota Burnaby | C38: 1122 | D38: 3600266904 | E38: 697585 | F38: CVI | H38: =+VLOOKUP(F38,Categories!A:B,2,) -> Inspection (CVI) | I38: 209.95 | J38: 0 | K38: 0 | L38: 0 | M38: =+I38+J38+K38-L38 -> 209.95 | N38: 10.5 | O38: 14.7 | P38: =+N38+O38 -> 25.2 | Q38: GST + PST | R38: =+ROUND(P38+M38,2) -> 235.15 | S38: bZ | T38: 50716
A39: 46035 | B39: Destination Toyota Burnaby | C39: 1122 | D39: 3600266904 | E39: 697599 | F39: CVI | H39: =+VLOOKUP(F39,Categories!A:B,2,) -> Inspection (CVI) | I39: 209.95 | J39: 25 | K39: 0 | L39: 0 | M39: =+I39+J39+K39-L39 -> 234.95 | N39: 11.75 | O39: 16.45 | P39: =+N39+O39 -> 28.2 | Q39: GST + PST | R39: =+ROUND(P39+M39,2) -> 263.15 | S39: bZ | T39: 50253
A40: 46043 | B40: OpenRoad Toyota Richmond | C40: 1078 | D40: 3600267134 | E40: 356916 | F40: CVI | H40: =+VLOOKUP(F40,Categories!A:B,2,) -> Inspection (CVI) | I40: 515.85 | J40: 0 | K40: 0 | L40: 0 | M40: =+I40+J40+K40-L40 -> 515.85 | N40: 25.79 | O40: 0 | P40: =+N40+O40 -> 25.79 | Q40: GST only | R40: =+ROUND(P40+M40,2) -> 541.64 | S40: bZ | T40: 49660
A41: 46043 | B41: OpenRoad Toyota Richmond | C41: 1078 | D41: 3600267134 | E41: 356918 | F41: CVI | H41: =+VLOOKUP(F41,Categories!A:B,2,) -> Inspection (CVI) | I41: 515.85 | J41: 0 | K41: 0 | L41: 0 | M41: =+I41+J41+K41-L41 -> 515.85 | N41: 25.79 | O41: 0 | P41: =+N41+O41 -> 25.79 | Q41: GST only | R41: =+ROUND(P41+M41,2) -> 541.64 | S41: bZ | T41: 49855
A42: 46051 | B42: Westminster Toyota | C42: 1117 | D42: 3600267494 | E42: 385164 | F42: Tire replacement | H42: =+VLOOKUP(F42,Categories!A:B,2,) -> Tires & Wheels | I42: 110.98 | J42: 13.32 | K42: 947.3 | L42: 0 | M42: =+I42+J42+K42-L42 -> 1071.6 | N42: 53.58 | O42: 75.01 | P42: =+N42+O42 -> 128.59 | Q42: GST + PST | R42: =+ROUND(P42+M42,2) -> 1200.19 | S42: bZ | T42: 50229
A43: 46051 | B43: Westminster Toyota | C43: 1117 | D43: 3600267494 | E43: 386667 | F43: Tire replacement | H43: =+VLOOKUP(F43,Categories!A:B,2,) -> Tires & Wheels | I43: 369.9 | J43: 72.89 | K43: 1652.8 | L43: 0 | M43: =+I43+J43+K43-L43 -> 2095.59 | N43: 104.78 | O43: 146.69 | P43: =+N43+O43 -> 251.47 | Q43: GST + PST | R43: =+ROUND(P43+M43,2) -> 2347.06 | S43: bZ | T43: 50463
A44: 46051 | B44: Destination Toyota Burnaby | C44: 1122 | D44: 3600267496 | E44: 700246 | F44: Towing | H44: Service | I44: 0 | J44: 382.8 | K44: 0 | L44: 0 | M44: =+I44+J44+K44-L44 -> 382.8 | N44: 19.14 | O44: 0 | P44: =+N44+O44 -> 19.14 | Q44: GST only | R44: =+ROUND(P44+M44,2) -> 401.94 | S44: bZ | T44: 58201
A45: 46000 | B45: OpenRoad Toyota Richmond | C45: 1078 | D45: 3600263906 | E45: 353593 | F45: GST DEDUCTIBLE | H45: =+VLOOKUP(F45,Categories!A:B,2,) -> Financial / Admin | I45: 530.11 | M45: =J45+I45 -> 530.11 | P45: =+O45+N45 -> 0 | Q45: No Tax | R45: =P45+M45 -> 530.11 | S45: bZ | T45: 44818
A46: 46010 | B46: Destination Toyota Burnaby | C46: 1122 | D46: 3600265569 | E46: 378502 | F46: Mirai repair (damaged by influencer) | H46: Repair | I46: 1174.21 | J46: 1804.77 | K46: 490.7 | M46: =+I46+J46+K46 -> 3469.68 | N46: 173.49 | O46: 242.87 | P46: =+N46+O46 -> 416.36 | Q46: GST + PST | R46: =+M46+P46 -> 3886.04 | S46: Mirai | T46: 11789
A47: 46013 | B47: Destination Toyota Burnaby | C47: 1122 | D47: 3600265692 | E47: 695013 | F47: CVI | H47: =+VLOOKUP(F47,Categories!A:B,2,) -> Inspection (CVI) | I47: 492.15 | J47: 0 | K47: 7 | M47: =+I47+J47+K47 -> 499.15 | N47: 24.96 | O47: 34.94 | P47: =+N47+O47 -> 59.9 | Q47: GST + PST | R47: =P47+M47 -> 559.05 | S47: bZ | T47: 50706
A48: 46013 | B48: Destination Toyota Burnaby | C48: 1122 | D48: 3600265692 | E48: 695021 | F48: CVI | H48: =+VLOOKUP(F48,Categories!A:B,2,) -> Inspection (CVI) | I48: 633.15 | J48: 0 | K48: 0 | M48: =+I48+J48+K48 -> 633.15 | N48: 31.66 | O48: 44.32 | P48: =+N48+O48 -> 75.98 | Q48: GST + PST | R48: =P48+M48 -> 709.13 | S48: bZ | T48: 50388
A49: 46013 | B49: Destination Toyota Burnaby | C49: 1122 | D49: 3600265692 | E49: 695437 | F49: CVI | H49: =+VLOOKUP(F49,Categories!A:B,2,) -> Inspection (CVI) | I49: 449.15 | J49: 0 | K49: 0 | M49: =+I49+J49+K49 -> 449.15 | N49: 22.46 | O49: 31.44 | P49: =+N49+O49 -> 53.9 | Q49: GST + PST | R49: =P49+M49 -> 503.05 | S49: bZ | T49: 51242
A50: 46013 | B50: Destination Toyota Burnaby | C50: 1122 | D50: 3600265692 | E50: 695824 | F50: CVI | H50: =+VLOOKUP(F50,Categories!A:B,2,) -> Inspection (CVI) | I50: 209.95 | J50: 320 | K50: 0 | M50: =+I50+J50+K50 -> 529.95 | N50: 26.5 | O50: 37.1 | P50: =+N50+O50 -> 63.6 | Q50: GST + PST | R50: =P50+M50 -> 593.55 | S50: bZ | T50: 50816
A51: 46013 | B51: Destination Toyota Burnaby | C51: 1122 | D51: 3600265692 | E51: 696231 | F51: CVI | H51: =+VLOOKUP(F51,Categories!A:B,2,) -> Inspection (CVI) | I51: 209.95 | J51: 0 | K51: 0 | M51: =J51+I51 -> 209.95 | N51: 10.5 | O51: 14.7 | P51: =+N51+O51 -> 25.2 | Q51: GST + PST | R51: =P51+M51 -> 235.15 | S51: bZ | T51: 50334
A52: 46013 | B52: Destination Toyota Burnaby | C52: 1122 | D52: 3600265692 | E52: 696232 | F52: CVI | H52: =+VLOOKUP(F52,Categories!A:B,2,) -> Inspection (CVI) | I52: 669.95 | J52: 0 | K52: 0 | M52: =J52+I52 -> 669.95 | N52: 33.5 | O52: 46.9 | P52: =+N52+O52 -> 80.4 | Q52: GST + PST | R52: =P52+M52 -> 750.35 | S52: bZ | T52: 50998
A53: 46013 | B53: Destination Toyota Burnaby | C53: 1122 | D53: 3600265693 | E53: 378947 | F53: bZ Repair (windshield) | H53: Repair | I53: 718.2 | J53: 1641.94 | K53: 7.72 | M53: 2367.86 | N53: 118.39 | O53: 165.75 | P53: 284.14 | Q53: GST + PST | R53: 2652 | S53: bZ | T53: 50816
A54: 46013 | B54: Destination Toyota Burnaby | C54: 1122 | D54: 3600265703 | E54: 378746 | F54: bZ repair (front colision) | H54: Repair | I54: 4027.77 | J54: 1054.85 | L54: 4938.41 | M54: 144.21 | N54: 254.13 | O54: 355.79 | P54: 609.92 | Q54: GST + PST | R54: 754.13 | S54: bZ | T54: 50388
A55: 46013 | B55: Destination Toyota Burnaby | C55: 1122 | D55: 3600265703 | E55: 378817 | F55: Credit for #378746 | H55: =+VLOOKUP(F55,Categories!A:B,2,) -> Financial / Admin | J55: -23 | M55: -23 | N55: 0 | O55: 0 | P55: 0 | Q55: NO TAX | R55: -23 | S55: bZ | T55: 50388
A56: 46014 | B56: Westminster Toyota | C56: 1117 | D56: 3600265714 | E56: 386103 | F56: Condition (Brake) | H56: Repair | I56: 184.95 | J56: 22.19 | M56: 207.14 | N56: 10.357 | O56: 14.4998 | P56: 24.8568 | Q56: GST + PST | R56: 232 | S56: bZ | T56: 96921
A57: 45952 | B57: Destination Toyota Burnaby | C57: 1122 | D57: 3600260261 | E57: 684408 | F57: 4 tires swap | H57: =+VLOOKUP(F57,Categories!A:B,2,) -> Tires & Wheels | I57: 1775.08 | J57: 26 | M57: 1801.08 | N57: 90.05 | O57: 126.08 | P57: 216.13 | Q57: GST + PST | R57: 2017.21 | S57: bZ | T57: 27970
A58: 45952 | B58: Destination Toyota Burnaby | C58: 1122 | D58: 3600260261 | E58: 688284 | F58: towing & recharge | H58: =+VLOOKUP(F58,Categories!A:B,2,) -> Fuel & Recharge | I58: 382.8 | J58: 25 | M58: 407.8 | N58: 20.39 | O58: 28.55 | P58: 48.94 | Q58: GST + PST | R58: 456.74 | S58: bZ | T58: 58201
A59: 45952 | B59: Destination Toyota Burnaby | C59: 1122 | D59: NA | E59: 377642 | F59: Rear end colision | H59: Repair | I59: 3272.15 | J59: 517.94 | M59: 3790.09 | N59: 189.51 | O59: 265.31 | P59: 454.82 | Q59: GST + PST | R59: 2689.51 | S59: bZ | T59: 50816
A60: 45953 | B60: Destination Toyota Burnaby | C60: 1122 | D60: 3600260302 | E60: 687801 | F60: service and recharge | H60: =+VLOOKUP(F60,Categories!A:B,2,) -> Fuel & Recharge | I60: 75 | J60: 0 | M60: 75 | N60: 0 | O60: 0 | P60: 0 | Q60: no tax | R60: 75 | S60: bZ | T60: 94807
A61: 45953 | B61: OpenRoad Toyota Richmond | C61: 1078 | D61: 3600260303 | E61: 347951 | F61: Body shop Repairs | H61: Repair | I61: 1109.82 | J61: 0 | M61: 1109.82 | N61: 55.49 | O61: 0 | P61: 55.49 | Q61: GST only | R61: 1165.31 | S61: bZ | T61: 49855
A62: 45953 | B62: Destination Toyota Burnaby | C62: 1122 | D62: 3600260337 | E62: 690239 | F62: kinto recharge | H62: =+VLOOKUP(F62,Categories!A:B,2,) -> Fuel & Recharge | I62: 25 | J62: 0 | M62: 25 | N62: 0 | O62: 0 | P62: 0 | Q62: no tax | R62: 25 | S62: bZ | T62: 50388
A63: 45953 | B63: Destination Toyota Burnaby | C63: 1122 | D63: 3600260337 | E63: 689922 | F63: kinto refueling | H63: =+VLOOKUP(F63,Categories!A:B,2,) -> Fuel & Recharge | I63: 45 | M63: 45 | P63: 0 | Q63: no tax | R63: 45 | S63: bZ | T63: 51224
A64: 45882 | B64: OpenRoad Toyota Richmond | C64: 1078 | D64: 3600255097 | E64: 321925 | F64: OTA Key Install | H64: =+VLOOKUP(F64,Categories!A:B,2,) -> Hardware & OTA | I64: 171.95 | M64: 171.95 | N64: 8.6 | O64: 12.04 | P64: 20.64 | Q64: GST + PST | R64: 192.59 | S64: Mirai | T64: 11764
A65: 45882 | B65: OpenRoad Toyota Richmond | C65: 1078 | D65: 3600255097 | E65: 337792 | F65: GST recoverable | H65: =+VLOOKUP(F65,Categories!A:B,2,) -> Financial / Admin | I65: 132.28 | M65: 132.28 | N65: 0 | O65: 0 | P65: 0 | Q65: no tax | R65: 132.28 | S65: Mirai | T65: 11764
A66: 45882 | B66: Jim Pattison Toyota Surrey | C66: 1088 | D66: 3600255098 | E66: 531588 | F66: HW removal | H66: =+VLOOKUP(F66,Categories!A:B,2,) -> Hardware & OTA | I66: 165 | J66: 10.99 | M66: 175.99 | N66: 8.8 | P66: 8.8 | Q66: GST | R66: 184.79 | S66: bZ | T66: 46096
A67: 45882 | B67: Jim Pattison Toyota Surrey | C67: 1088 | D67: 3600255098 | E67: 531587 | F67: HW removal | H67: =+VLOOKUP(F67,Categories!A:B,2,) -> Hardware & OTA | I67: 165 | J67: 10.99 | M67: 175.99 | N67: 8.8 | O67: 0 | P67: 8.8 | Q67: GST | R67: 184.79 | S67: bZ | T67: 45528
A68: 45882 | B68: Jim Pattison Toyota Surrey | C68: 1088 | D68: 3600255098 | E68: 528857 | F68: Service | H68: Service | I68: 89.9 | J68: 8.99 | M68: 98.89 | N68: 4.95 | O68: 6.92 | P68: 11.87 | Q68: GST + PST | R68: 110.76 | S68: bZ | T68: 23415
A69: 45882 | B69: Jim Pattison Toyota Surrey | C69: 1088 | D69: 3600255098 | E69: 528846 | F69: tire puncture | H69: =+VLOOKUP(F69,Categories!A:B,2,) -> Tires & Wheels | I69: 49.5 | J69: 4.95 | M69: 54.45 | N69: 2.73 | O69: 3.82 | P69: 6.55 | Q69: GST + PST | R69: 61 | S69: bZ | T69: 46096
A70: 45882 | B70: Kelowna | D70: 3600255096 | E70: 394414 | F70: Mirai tire | H70: =+VLOOKUP(F70,Categories!A:B,2,) -> Tires & Wheels | I70: 562 | J70: 471.87 | M70: 1033.87 | N70: 51.69 | O70: 72.37 | P70: 124.06 | Q70: GST + PST | R70: 1157.93 | S70: Mirai | T70: 11764
A71: 45862 | B71: Destination Toyota Burnaby | C71: 1122 | D71: 3600254068 | E71: 679480 | F71: Battery Replacement | H71: Repair | I71: 55.2 | J71: 280.49 | M71: 335.69 | N71: 16.78 | O71: 23.49 | P71: 40.27 | Q71: GST | R71: 375.96 | S71: Mirai | T71: 11789
A72: 45820 | B72: Westminster Toyota | C72: 1117 | D72: 3600250023 | E72: 374012 | F72: Battery replacement | H72: Repair | I72: 462.43 | J72: 28.07 | M72: 490.5 | N72: 24.53 | O72: 34.34 | P72: 58.87 | Q72: GST | R72: 549.37 | S72: bZ | T72: 58341
A73: 45820 | B73: Destination Toyota Burnaby | C73: 1122 | D73: 3600250022 | E73: 675038 | F73: Mirai refuel fee | H73: =+VLOOKUP(F73,Categories!A:B,2,) -> Fuel & Recharge | I73: 33.75 | J73: 25 | M73: 58.75 | N73: 2.94 | O73: 4.11 | P73: 7.05 | Q73: GST | R73: 65.8 | S73: Mirai | T73: 11786
A74: 45820 | B74: Westminster Toyota | C74: 1117 | D74: 3600250067 | E74: 372562 | F74: Battery replacement | H74: Repair | I74: 215.94 | J74: 320.42 | M74: 536.36 | N74: 26.82 | O74: 37.55 | P74: 64.37 | Q74: GST | R74: 600.73 | S74: Mirai | T74: 08438
A75: 45834 | B75: Westminster Toyota | C75: 1117 | D75: 3600251984 | E75: 371588 | F75: Battery Replacement | H75: Repair | I75: 300.47 | J75: 8.64 | M75: 309.11 | N75: 15.46 | O75: 21.64 | P75: 37.1 | Q75: GST + PST | R75: 346.21 | S75: bZ | T75: 58341
A76: 45834 | B76: Westminster Toyota | C76: 1117 | D76: 3600251984 | E76: 374753 | F76: Battery Replacement | H76: Repair | I76: 426.09 | J76: 15.12 | M76: 441.21 | N76: 22.06 | O76: 30.88 | P76: 52.94 | Q76: GST + PST | R76: 494.15 | S76: Mirai | T76: 11766
A77: 45834 | B77: Westminster Toyota | C77: 1117 | D77: 3600251984 | E77: 374990 | F77: Tire Replacement | H77: =+VLOOKUP(F77,Categories!A:B,2,) -> Tires & Wheels | I77: 442.98 | J77: 12.49 | M77: 455.47 | N77: 22.77 | O77: 31.88 | P77: 54.65 | Q77: GST + PST | R77: 510.12 | S77: bZ | T77: 58341
A78: 45792 | B78: OpenRoad Toyota Richmond | C78: 1078 | D78: 3600248581 | E78: 329031 | F78: Insurance claim/ GST only | H78: =+VLOOKUP(F78,Categories!A:B,2,) -> Financial / Admin | I78: 362.89 | M78: 362.89 | P78: 0 | Q78: GST only | R78: 362.89 | S78: bZ | T78: 29083
A79: 45792 | B79: OpenRoad Toyota Richmond | C79: 1078 | D79: 3600248581 | E79: 329032 | F79: Insurance claim | H79: =+VLOOKUP(F79,Categories!A:B,2,) -> Financial / Admin | I79: 2500 | M79: 2500 | P79: 0 | Q79: no tax | R79: 2500 | S79: bZ | T79: 29083
A80: 45804 | B80: Destination Toyota Burnaby | C80: 1122 | D80: 3600248798 | E80: 670330 | F80: Hw removal | H80: =+VLOOKUP(F80,Categories!A:B,2,) -> Hardware & OTA | I80: 184 | J80: 10.99 | M80: =+I80+J80 -> 194.99 | N80: =+M80*0.05 -> 9.7495 | O80: =+M80*0.06 -> 11.6994 | P80: =+O80+N80 -> 21.4489 | Q80: GST + PST | R80: =+P80+M80 -> 216.4389 | S80: Mirai | T80: 08371
A81: 45804 | B81: Destination Toyota Burnaby | C81: 1122 | D81: 3600248798 | E81: 670330 | F81: battery replacement | H81: Repair | I81: =239.2-I80 -> 55.2 | K81: =285.97-J80 -> 274.98 | M81: =+I81+K81 -> 330.18 | N81: =+M81*0.05 -> 16.509 | O81: =+M81*0.07 -> 23.1126 | P81: =+N81+O81 -> 39.6216 | Q81: GST + PST | R81: =+M81+P81 -> 369.8016 | S81: Mirai | T81: 08371
A82: 45804 | B82: Jim Pattison Toyota Surrey | C82: 1088 | D82: 3600248799 | E82: 530806 | F82: 2 new tires + balance | H82: =+VLOOKUP(F82,Categories!A:B,2,) -> Tires & Wheels | I82: 916.06 | J82: 13 | M82: 929.06 | N82: 46.45 | O82: 65.03 | P82: 111.48 | Q82: GST + PST | R82: 1040.54 | S82: bZ | T82: 27333
A83: 45750 | B83: Destination Toyota Burnaby | C83: 1122 | D83: 3600246344 | E83: 667667 | F83: HW removal | H83: =+VLOOKUP(F83,Categories!A:B,2,) -> Hardware & OTA | I83: 184 | J83: 10.99 | M83: 194.99 | N83: 9.7495 | O83: 13.6493 | P83: 23.3988 | Q83: GST + PST | R83: 218.3888 | S83: Mirai | T83: 11741
A84: 45750 | B84: Westminster Toyota | C84: 1117 | D84: 3600246345 | E84: 369007 | F84: HW removal | H84: =+VLOOKUP(F84,Categories!A:B,2,) -> Hardware & OTA | I84: 209.94 | J84: 37.69 | M84: 247.63 | N84: 12.3815 | O84: 17.3341 | P84: 29.7156 | Q84: GST + PST | R84: 277.3456 | S84: Mirai | T84: 11724
A85: 45750 | B85: Westminster Toyota | C85: 1117 | D85: 3600246345 | E85: 369006 | F85: HW removal | H85: =+VLOOKUP(F85,Categories!A:B,2,) -> Hardware & OTA | I85: 209.94 | J85: 39.07 | M85: 249.01 | N85: 12.4505 | O85: 17.4307 | P85: 29.8812 | Q85: GST + PST | R85: 278.8912 | S85: Mirai | T85: 11714
A86: 45750 | B86: Westminster Toyota | C86: 1117 | D86: 3600246345 | E86: 369005 | F86: HW removal | H86: =+VLOOKUP(F86,Categories!A:B,2,) -> Hardware & OTA | I86: 209.94 | J86: 37.69 | M86: 247.63 | N86: 12.3815 | O86: 17.3341 | P86: 29.7156 | Q86: GST + PST | R86: 277.3456 | S86: Mirai | T86: 11705
A87: 45750 | B87: OpenRoad Toyota Richmond | C87: 1078 | D87: 3600246346 | E87: 323328 | F87: HW removal | H87: =+VLOOKUP(F87,Categories!A:B,2,) -> Hardware & OTA | I87: 171.95 | M87: 171.95 | N87: 8.5975 | O87: 12.0365 | P87: 20.634 | Q87: GST + PST | R87: 192.584 | S87: Mirai | T87: 11691
A88: 45756 | B88: OpenRoad Toyota Richmond | C88: 1078 | D88: 3600246787 | E88: 320536 | F88: HW install | H88: =+VLOOKUP(F88,Categories!A:B,2,) -> Hardware & OTA | I88: 171.95 | M88: 171.95 | N88: 8.5975 | O88: 12.0365 | P88: 20.634 | Q88: GST + PST | R88: 192.584 | S88: bZ | T88: 58141
A89: 45756 | B89: OpenRoad Toyota Richmond | C89: 1078 | D89: 3600246787 | E89: 320538 | F89: HW install | H89: =+VLOOKUP(F89,Categories!A:B,2,) -> Hardware & OTA | I89: 171.95 | M89: 171.95 | N89: 8.5975 | O89: 12.0365 | P89: 20.634 | Q89: GST + PST | R89: 192.584 | S89: bZ | T89: 58188
A90: 45756 | B90: OpenRoad Toyota Richmond | C90: 1078 | D90: 3600246787 | E90: 320534 | F90: HW install | H90: =+VLOOKUP(F90,Categories!A:B,2,) -> Hardware & OTA | I90: 171.95 | M90: 171.95 | N90: 8.5975 | O90: 12.0365 | P90: 20.634 | Q90: GST + PST | R90: 192.584 | S90: bZ | T90: 94733
A91: 45756 | B91: OpenRoad Toyota Richmond | C91: 1078 | D91: 3600246787 | E91: 320533 | F91: HW install | H91: =+VLOOKUP(F91,Categories!A:B,2,) -> Hardware & OTA | I91: 171.95 | M91: 171.95 | N91: 8.5975 | O91: 12.0365 | P91: 20.634 | Q91: GST + PST | R91: 192.584 | S91: bZ | T91: 94722
A92: 45762 | B92: OpenRoad Toyota Richmond | C92: 1078 | D92: 3600246872 | E92: 321923 | F92: HW install | H92: =+VLOOKUP(F92,Categories!A:B,2,) -> Hardware & OTA | I92: 171.95 | M92: 171.95 | N92: 8.5975 | O92: 12.0365 | P92: 20.634 | Q92: GST + PST | R92: 192.584 | S92: Mirai | T92: 11754
A93: 45772 | B93: Westminster Toyota | C93: 1117 | D93: 3600247173 | E93: 370445 | F93: CVI | H93: =+VLOOKUP(F93,Categories!A:B,2,) -> Inspection (CVI) | I93: 215.94 | J93: 25.91 | M93: 241.85 | N93: 12.0925 | O93: 16.9295 | P93: 29.022 | Q93: GST + PST | R93: 270.872 | S93: bZ | T93: 58341
A94: 45772 | B94: Westminster Toyota | C94: 1117 | D94: 3600247173 | E94: 370389 | F94: CVI | H94: =+VLOOKUP(F94,Categories!A:B,2,) -> Inspection (CVI) | I94: 215.94 | J94: 25.91 | M94: 241.85 | N94: 12.0925 | O94: 16.9295 | P94: 29.022 | Q94: GST + PST | R94: 270.872 | S94: bZ | T94: 94891
A95: 45777 | B95: Westminster Toyota | C95: 1117 | D95: 3600247572 | E95: 3600246885 | F95: Difference on purchase price | H95: =+VLOOKUP(F95,Categories!A:B,2,) -> Financial / Admin | I95: 1000 | M95: 1000 | N95: 50 | P95: 50 | Q95: GST | R95: 1050 | S95: bZ | T95: 58341
A96: 45729 | B96: Westminster Toyota | C96: 1117 | D96: 3600243525 | E96: 260176 | F96: wheel hub | H96: =+VLOOKUP(F96,Categories!A:B,2,) -> Tires & Wheels | I96: 109.82 | M96: 109.82 | N96: 5.491 | O96: 7.6874 | P96: 13.1784 | Q96: GST + PST | R96: 122.9984 | S96: bZ | T96: 45366
A97: 45729 | B97: Westminster Toyota | C97: 1117 | D97: 3600243525 | E97: 366633 | F97: hw unisntall | H97: =+VLOOKUP(F97,Categories!A:B,2,) -> Hardware & OTA | I97: 262.43 | J97: 43.99 | M97: 306.42 | N97: 15.321 | O97: 21.4494 | P97: 36.7704 | Q97: GST + PST | R97: 343.1904 | S97: bZ | T97: 45366
A98: 45729 | B98: Jim Pattison Toyota Surrey | C98: 1088 | D98: 3600243526 | E98: 14194893 | F98: smashed window | H98: Repair | I98: 1437.38 | M98: 1437.38 | N98: 71.869 | O98: 100.6166 | P98: 172.4856 | Q98: GST + PST | R98: 1609.8656 | S98: bZ | T98: 50998
A99: 45729 | B99: Destination Toyota Burnaby | C99: 1122 | D99: 3600243527 | E99: 664462 | F99: HW removal | H99: =+VLOOKUP(F99,Categories!A:B,2,) -> Hardware & OTA | I99: 184 | J99: 10.99 | M99: 194.99 | N99: 9.7495 | O99: 13.6493 | P99: 23.3988 | Q99: GST + PST | R99: 218.3888 | S99: bZ | T99: 45139
A100: 45729 | B100: Destination Toyota Burnaby | C100: 1122 | D100: 3600243527 | E100: 664466 | F100: HW removal | H100: =+VLOOKUP(F100,Categories!A:B,2,) -> Hardware & OTA | I100: 184 | J100: 10.99 | M100: 194.99 | N100: 9.7495 | O100: 13.6493 | P100: 23.3988 | Q100: GST + PST | R100: 218.3888 | S100: bZ | T100: 28495
...

Sheet Categories
A2: GST portion for repairs | B2: Financial / Admin
A3: Wheel cover replacement | B3: Tires & Wheels
A4: Brakes repair | B4: Maintenance & Repair
A5: Body shop | B5: Maintenance & Repair
A6: Rim repair & alignment | B6: Tires & Wheels
A7: Window Bezel Replacement | B7: Maintenance & Repair
A8: Hydrogen refuel | B8: Fuel & Recharge
A9: Windshield replacement | B9: Maintenance & Repair
A10: deductible portion plus GST | B10: Financial / Admin
A11: Hubcap replacement | B11: Tires & Wheels
A12: Extra cleaning & recharge | B12: Fuel & Recharge
A13: Tire replacement | B13: Tires & Wheels
... A66: bZ repair (front colision) | B66: Maintenance & Repair
