Workbook

Sheet Dep TCCI
B2: Year | C2: Dep/24 | D2: Model | E2: Trim | F2: RV | G2: Rebate $ | H2: Owner | I2: VIN | J2: Purchase Price | K2: Price (w/o Rebate) | L2: Actual Paid (BOS) | M2: Purchase Date | N2: Purchase Month | O2: Offboard Date | P2: Offboard Month | Q2: Months on Program | R2: Accident | S2: Odometer | T2: Sold Month | U2: Sold Price | V2: B/E Price | W2: G/L | X2: Fees (w/o tax) | Y2: Fees (w/ tax) | Z2: Actual Total Dep | AA2: Dep/24 [TCI accounting view] | AB2: Total Depreciation [TCI accounting view] | AC2: Diff.
D4: iZEV w/o Prov | E4: RV | F4: 30000
B5: MY23 | C5: =(L5-F5)/24 -> 630.92917 | D5: bZ4X | E5: LE | F5: =F4 -> 30000 | G5: =5000 -> 5000 | H5: TCCI | I5: JTMAAAAAXPA027970 | J5: =47345+1825+958+463.71+20-5000 -> 45611.71 | K5: =J5+5000 -> 50611.71 | L5: 45142.3 | M5: 45284 | N5: 45261 | O5: =TODAY() -> 46106 | Q5: =(YEAR(O5) - YEAR(M5)) * 12 + MONTH(O5) - MONTH(M5) + 1 -> 28 | R5: =VLOOKUP(I5, [1]Fleet!$C:$V, 20, FALSE) -> Yes | S5: =VLOOKUP(I5, [1]Fleet!$C:$Q, 14, FALSE) -> 76861 | V5: =L5-(C5*Q5) -> 27476.283 | Z5: =Q5*C5 -> 17666.017 | AA5: =(J5-F5)/24 -> 650.48792 | AB5: =+AA5*Q5 -> 18213.662 | AC5: =+Z5-AB5 -> -547.645
D7: iZEV w/o Prov | E7: RV | F7: 30000
B8: MY23 | C8: =(L8-F8)/24 -> 838.62375 | D8: bZ4X | E8: XLE | F8: =F7 -> 30000 | G8: =5000 -> 5000 | H8: TCCI | I8: JTMABACA2PA045471 | J8: =52058+1825+958+498.02+20-5000 -> 50359.02 | K8: =J8+5000 -> 55359.02 | L8: 50126.97 | M8: 45284 | N8: 45261 | O8: 45708 | P8: 45689 | Q8: =(YEAR(O8) - YEAR(M8)) * 12 + MONTH(O8) - MONTH(M8) + 1 -> 15 | R8: =VLOOKUP(I8, [1]Fleet!$C:$V, 20, FALSE) -> No | S8: =VLOOKUP(I8, [1]Fleet!$C:$Q, 14, FALSE) -> 44327 | T8: 45717 | U8: 34090 | V8: =L8-(C8*Q8) -> 37547.614 | W8: =U8-V8 -> -3457.6138 | Z8: =Q8*C8 -> 12579.356 | AA8: =(J8-F8)/24 -> 848.2925 | AB8: =+AA8*Q8 -> 12724.387 | AC8: =+Z8-AB8 -> -145.03125
D10: w/ iZEV + Prov | E10: RV | F10: 30000
B11: MY23 | C11: =(L11-$F$11)/24 -> 630.92917 | D11: bZ4X | E11: LE | F11: =F10 -> 30000 | G11: =5000+3000 -> 8000 | H11: TCCI | I11: JTMAAAAA8PA028907 | J11: =((L11+G11)/1.05)-G11 -> 42611.714 | K11: =((L11+G11)/1.05) -> 50611.714 | L11: 45142.3 | M11: 45284 | N11: 45261 | O11: 45708 | P11: 45689 | Q11: =(YEAR(O11) - YEAR(M11)) * 12 + MONTH(O11) - MONTH(M11) + 1 -> 15 | R11: =VLOOKUP(I11, [1]Fleet!$C:$V, 20, FALSE) -> Yes | S11: =VLOOKUP(I11, [1]Fleet!$C:$Q, 14, FALSE) -> 48902 | T11: 45748 | U11: 29990 | V11: =L11-(C11*Q11) -> 35678.363 | W11: =U11-V11 -> -5688.3625 | Z11: =Q11*C11 -> 9463.9375 | AA11: =(J11-$F$11)/24 -> 525.4881 | AB11: =+AA11*Q11 -> 7882.3214 | AC11: =+Z11-AB11 -> 1581.6161
B12: MY23 | C12: =(L12-$F$11)/24 -> 630.92917 | D12: bZ4X | E12: LE | G12: =5000+3000 -> 8000 | H12: TCCI | I12: JTMAAAAA6PA023415 | J12: =((L12+G12)/1.05)-G12 -> 42611.714 | K12: =((L12+G12)/1.05) -> 50611.714 | L12: 45142.3 | M12: 45284 | N12: 45261 | O12: 45738 | P12: 45717 | Q12: =(YEAR(O12) - YEAR(M12)) * 12 + MONTH(O12) - MONTH(M12) + 1 -> 16 | R12: =VLOOKUP(I12, [1]Fleet!$C:$V, 20, FALSE) -> No | S12: =VLOOKUP(I12, [1]Fleet!$C:$Q, 14, FALSE) -> 45512 | V12: =L12-(C12*Q12) -> 35047.433 | Z12: =Q12*C12 -> 10094.867 | AA12: =(J12-$F$11)/24 -> 525.4881 | AB12: =+AA12*Q12 -> 8407.8095 | AC12: =+Z12-AB12 -> 1687.0571
B13: MY23 | C13: =(L13-$F$11)/24 -> 630.92917 | D13: bZ4X | E13: LE | G13: =5000+3000 -> 8000 | H13: TCCI | I13: JTMAAAAA2PA027333 | J13: =((L13+G13)/1.05)-G13 -> 42611.714 | K13: =((L13+G13)/1.05) -> 50611.714 | L13: 45142.3 | M13: 45284 | N13: 45261 | O13: =TODAY() -> 46106 | Q13: =(YEAR(O13) - YEAR(M13)) * 12 + MONTH(O13) - MONTH(M13) + 1 -> 28 | R13: =VLOOKUP(I13, [1]Fleet!$C:$V, 20, FALSE) -> Yes | S13: =VLOOKUP(I13, [1]Fleet!$C:$Q, 14, FALSE) -> 89435 | V13: =L13-(C13*Q13) -> 27476.283 | Z13: =Q13*C13 -> 17666.017 | AA13: =(J13-$F$11)/24 -> 525.4881 | AB13: =+AA13*Q13 -> 14713.667 | AC13: =+Z13-AB13 -> 2952.35
D15: w/ iZEV + Prov | E15: RV | F15: 30000
B16: MY23 | C16: =(L16-$F$16)/24 -> 838.62375 | D16: bZ4X | E16: XLE | F16: =F15 -> 30000 | G16: =5000+3000 -> 8000 | H16: TCCI | I16: JTMABACA9PA044818 | J16: =((L16+G16)/1.05)-G16 -> 47359.019 | K16: =((L16+G16)/1.05) -> 55359.019 | L16: 50126.97 | M16: 45284 | N16: 45261 | O16: =TODAY() -> 46106 | Q16: =(YEAR(O16) - YEAR(M16)) * 12 + MONTH(O16) - MONTH(M16) + 1 -> 28 | R16: =VLOOKUP(I16, [1]Fleet!$C:$V, 20, FALSE) -> Yes | S16: =VLOOKUP(I16, [1]Fleet!$C:$Q, 14, FALSE) -> 29935 | V16: =L16-(C16*Q16) -> 26645.505 | Z16: =Q16*C16 -> 23481.465
B17: MY23 | C17: =(L17-$F$16)/24 -> 838.62375 | D17: bZ4X | E17: XLE | G17: =5000+3000 -> 8000 | H17: TCCI | I17: JTMABACA7PA046096 | J17: =((L17+G17)/1.05)-G17 -> 47359.019 | K17: =((L17+G17)/1.05) -> 55359.019 | L17: 50126.97 | M17: 45284 | N17: 45261 | O17: 45738 | P17: 45717 | Q17: =(YEAR(O17) - YEAR(M17)) * 12 + MONTH(O17) - MONTH(M17) + 1 -> 16 | R17: =VLOOKUP(I17, [1]Fleet!$C:$V, 20, FALSE) -> Yes | S17: =VLOOKUP(I17, [1]Fleet!$C:$Q, 14, FALSE) -> 59450 | T17: 45809 | U17: 29400 | V17: =L17-(C17*Q17) -> 36708.99 | W17: =U17-V17 -> -7308.99 | X17: =205+5+20.75+15+90+10+10+25+88 -> 468.75 | Y17: =X17*1.05 -> 492.1875 | Z17: =Q17*C17 -> 13417.98 | AA17: =(J16-$F$16)/24 -> 723.29246 | AB17: =+AA17*Q17 -> 11572.679 | AC17: =+Z17-AB17 -> 1845.3006
B18: MY23 | C18: =(L18-$F$16)/24 -> 838.62375 | D18: bZ4X | E18: XLE | G18: =5000+3000 -> 8000 | H18: TCCI | I18: JTMABACA5PA045528 | J18: =((L18+G18)/1.05)-G18 -> 47359.019 | K18: =((L18+G18)/1.05) -> 55359.019 | L18: 50126.97 | M18: 45284 | N18: 45261 | O18: 45738 | P18: 45717 | Q18: =(YEAR(O18) - YEAR(M18)) * 12 + MONTH(O18) - MONTH(M18) + 1 -> 16 | R18: =VLOOKUP(I18, [1]Fleet!$C:$V, 20, FALSE) -> Yes | S18: =VLOOKUP(I18, [1]Fleet!$C:$Q, 14, FALSE) -> 35431 | T18: 45809 | U18: 32400 | V18: =L18-(C18*Q18) -> 36708.99 | W18: =U18-V18 -> -4308.99 | X18: =205+5+20.75+15+45+90+10+10+25+88 -> 513.75 | Y18: =X18*1.05 -> 539.4375 | Z18: =Q18*C18 -> 13417.98 | AA18: =(J17-$F$16)/24 -> 723.29246 | AB18: =+AA18*Q18 -> 11572.679 | AC18: =+Z18-AB18 -> 1845.3006
B19: MY23 | C19: =(L19-$F$16)/24 -> 838.62375 | D19: bZ4X | E19: XLE | G19: =5000+3000 -> 8000 | H19: TCCI | I19: JTMABACA7PA042856 | J19: =((L19+G19)/1.05)-G19 -> 47359.019 | K19: =((L19+G19)/1.05) -> 55359.019 | L19: 50126.97 | M19: 45284 | N19: 45261 | O19: 45738 | P19: 45717 | Q19: =(YEAR(O19) - YEAR(M19)) * 12 + MONTH(O19) - MONTH(M19) + 1 -> 16 | R19: =VLOOKUP(I19, [1]Fleet!$C:$V, 20, FALSE) -> No | S19: =VLOOKUP(I19, [1]Fleet!$C:$Q, 14, FALSE) -> 41898 | T19: 45809 | U19: 31400 | V19: =L19-(C19*Q19) -> 36708.99 | W19: =U19-V19 -> -5308.99 | X19: =205+5+20.75+15+90+10+10+25+88 -> 468.75 | Y19: =X19*1.05 -> 492.1875 | Z19: =Q19*C19 -> 13417.98 | AA19: =(J18-$F$16)/24 -> 723.29246 | AB19: =+AA19*Q19 -> 11572.679 | AC19: =+Z19-AB19 -> 1845.3006
B20: MY23 | C20: =(L20-$F$16)/24 -> 838.62375 | D20: bZ4X | E20: XLE | G20: =5000+3000 -> 8000 | H20: TCCI | I20: JTMABACA1PA041363 | J20: =((L20+G20)/1.05)-G20 -> 47359.019 | K20: =((L20+G20)/1.05) -> 55359.019 | L20: 50126.97 | M20: 45284 | N20: 45261 | O20: 45738 | P20: 45717 | Q20: =(YEAR(O20) - YEAR(M20)) * 12 + MONTH(O20) - MONTH(M20) + 1 -> 16 | R20: =VLOOKUP(I20, [1]Fleet!$C:$V, 20, FALSE) -> Yes | S20: =VLOOKUP(I20, [1]Fleet!$C:$Q, 14, FALSE) -> 47136 | T20: 45809 | U20: 31400 | V20: =L20-(C20*Q20) -> 36708.99 | W20: =U20-V20 -> -5308.99 | X20: =205+5+20.75+15+90+10+10+25+88 -> 468.75 | Y20: =X20*1.05 -> 492.1875 | Z20: =Q20*C20 -> 13417.98 | AA20: =(J19-$F$16)/24 -> 723.29246 | AB20: =+AA20*Q20 -> 11572.679 | AC20: =+Z20-AB20 -> 1845.3006
D22: w/ iZEV | E22: RV | F22: 27500
B23: MY24 | C23: =(L23-$F$23)/24 -> 1018.5108 | D23: Mirai | E23: XLE | F23: =F22 -> 27500 | G23: 5000 | H23: TCCI | I23: JTDAAAAAXRA011741 | J23: =((L23+G23)/1.05)-G23 -> 49232.629 | K23: =((L23+G23)/1.05) -> 54232.629 | L23: 51944.26 | M23: 45566 | N23: 45566 | O23: 45735 | P23: 45717 | Q23: =(YEAR(O23) - YEAR(M23)) * 12 + MONTH(O23) - MONTH(M23) + 1 -> 6 | R23: =VLOOKUP(I23, [1]Fleet!$C:$V, 20, FALSE) -> No | S23: =VLOOKUP(I23, [1]Fleet!$C:$Q, 14, FALSE) -> 5925 | T23: 45748 | U23: 50589 | V23: =L23-(C23*Q23) -> 45833.195 | W23: =U23-V23 -> 4755.805 | Z23: =Q23*C23 -> 6111.065 | AA23: =(J23-$F$23)/24 -> 905.52619 | AB23: =+AA23*Q23 -> 5433.1571 | AC23: =+Z23-AB23 -> 677.90786
B24: MY24 | C24: =(L24-$F$23)/24 -> 1018.5108 | D24: Mirai | E24: XLE | G24: 5000 | H24: TCCI | I24: JTDAAAAAXRA011724 | J24: =((L24+G24)/1.05)-G24 -> 49232.629 | K24: =((L24+G24)/1.05) -> 54232.629 | L24: 51944.26 | M24: 45563 | N24: 45536 | O24: 45735 | P24: 45717 | Q24: =(YEAR(O24) - YEAR(M24)) * 12 + MONTH(O24) - MONTH(M24) + 1 -> 7 | R24: =VLOOKUP(I24, [1]Fleet!$C:$V, 20, FALSE) -> No | S24: =VLOOKUP(I24, [1]Fleet!$C:$Q, 14, FALSE) -> 9310 | T24: 45748 | U24: 48519.03 | V24: =L24-(C24*Q24) -> 44814.684 | W24: =U24-V24 -> 3704.3458 | Z24: =Q24*C24 -> 7129.5758 | AA24: =(J24-$F$23)/24 -> 905.52619 | AB24: =+AA24*Q24 -> 6338.6833 | AC24: =+Z24-AB24 -> 790.8925
B25: MY24 | C25: =(L25-$F$23)/24 -> 1018.5108 | D25: Mirai | E25: XLE | G25: 5000 | H25: TCCI | I25: JTDAAAAA6RA011705 | J25: =((L25+G25)/1.05)-G25 -> 49232.629 | K25: =((L25+G25)/1.05) -> 54232.629 | L25: 51944.26 | M25: 45563 | N25: 45536 | O25: 45735 | P25: 45717 | Q25: =(YEAR(O25) - YEAR(M25)) * 12 + MONTH(O25) - MONTH(M25) + 1 -> 7 | R25: =VLOOKUP(I25, [1]Fleet!$C:$V, 20, FALSE) -> No | S25: =VLOOKUP(I25, [1]Fleet!$C:$Q, 14, FALSE) -> 12502 | T25: 45748 | U25: 46731.51 | V25: =L25-(C25*Q25) -> 44814.684 | W25: =U25-V25 -> 1916.8258 | Z25: =Q25*C25 -> 7129.5758 | AA25: =(J25-$F$23)/24 -> 905.52619 | AB25: =+AA25*Q25 -> 6338.6833 | AC25: =+Z25-AB25 -> 790.8925
B26: MY24 | C26: =(L26-$F$23)/24 -> 1018.5108 | D26: Mirai | E26: XLE | G26: 5000 | H26: TCCI | I26: JTDAAAAA7RA011714 | J26: =((L26+G26)/1.05)-G26 -> 49232.629 | K26: =((L26+G26)/1.05) -> 54232.629 | L26: 51944.26 | M26: 45563 | N26: 45536 | O26: 45735 | P26: 45717 | Q26: =(YEAR(O26) - YEAR(M26)) * 12 + MONTH(O26) - MONTH(M26) + 1 -> 7 | R26: =VLOOKUP(I26, [1]Fleet!$C:$V, 20, FALSE) -> No | S26: =VLOOKUP(I26, [1]Fleet!$C:$Q, 14, FALSE) -> 3661 | T26: 45748 | U26: 51132.5 | V26: =L26-(C26*Q26) -> 44814.684 | W26: =U26-V26 -> 6317.8158 | Z26: =Q26*C26 -> 7129.5758 | AA26: =(J26-$F$23)/24 -> 905.52619 | AB26: =+AA26*Q26 -> 6338.6833 | AC26: =+Z26-AB26 -> 790.8925
B28: MY24 | C28: =(L28-$F$23)/24 -> 1243.0229 | D28: Mirai | E28: XLE | F28: Cannot locate BOS | G28: 0 | H28: TCCI | I28: JTDAAAAA3RA011645 | J28: =((L28+G28)/1.05)-G28 -> 54602.429 | K28: =((L28+G28)/1.05) -> 54602.429 | L28: 57332.55 | M28: 45435 | N28: 45413 | O28: 45596 | P28: 45566 | Q28: =(YEAR(O28) - YEAR(M28)) * 12 + MONTH(O28) - MONTH(M28) + 1 -> 6 | R28: =VLOOKUP(I28, [1]Fleet!$C:$V, 20, FALSE) -> Yes | S28: =VLOOKUP(I28, [1]Fleet!$C:$Q, 14, FALSE) -> 13709 | T28: 45627 | U28: 42918.63 | V28: =L28-(C28*Q28) -> 49874.413 | W28: =U28-V28 -> -6955.7825 | Z28: =Q28*C28 -> 7458.1375 | AA28: =(J28-$F$23)/24 -> 1129.2679 | AB28: =+AA28*Q28 -> 6775.6071 | AC28: =+Z28-AB28 -> 682.53036
B29: MY24 | C29: =(L29-$F$23)/24 -> 1243.0229 | D29: Mirai | E29: XLE | F29: Cannot locate BOS | G29: 0 | H29: TCCI | I29: JTDAAAAA2RA011684 | J29: =((L29+G29)/1.05)-G29 -> 54602.429 | K29: =((L29+G29)/1.05) -> 54602.429 | L29: 57332.55 | M29: 45435 | N29: 45413 | O29: 45596 | P29: 45566 | Q29: =(YEAR(O29) - YEAR(M29)) * 12 + MONTH(O29) - MONTH(M29) + 1 -> 6 | R29: =VLOOKUP(I29, [1]Fleet!$C:$V, 20, FALSE) -> No | S29: =VLOOKUP(I29, [1]Fleet!$C:$Q, 14, FALSE) -> 12648 | T29: 45627 | U29: 45932.1 | V29: =L29-(C29*Q29) -> 49874.413 | W29: =U29-V29 -> -3942.3125 | Z29: =Q29*C29 -> 7458.1375 | AA29: =(J29-$F$23)/24 -> 1129.2679 | AB29: =+AA29*Q29 -> 6775.6071 | AC29: =+Z29-AB29 -> 682.53036
B30: MY24 | C30: =(L30-$F$23)/24 -> 1243.0229 | D30: Mirai | E30: XLE | G30: 0 | H30: TCCI | I30: JTDAAAAA7RA011633 | J30: =((L30+G30)/1.05)-G30 -> 54602.429 | K30: =((L30+G30)/1.05) -> 54602.429 | L30: 57332.55 | M30: 45434 | N30: 45413 | O30: 45596 | P30: 45566 | Q30: =(YEAR(O30) - YEAR(M30)) * 12 + MONTH(O30) - MONTH(M30) + 1 -> 6 | R30: =VLOOKUP(I30, [1]Fleet!$C:$V, 20, FALSE) -> No | S30: =VLOOKUP(I30, [1]Fleet!$C:$Q, 14, FALSE) -> 11881 | T30: 45627 | U30: 47984.16 | V30: =L30-(C30*Q30) -> 49874.413 | W30: =U30-V30 -> -1890.2525 | Z30: =Q30*C30 -> 7458.1375 | AA30: =(J30-$F$23)/24 -> 1129.2679 | AB30: =+AA30*Q30 -> 6775.6071 | AC30: =+Z30-AB30 -> 682.53036
B31: MY24 | C31: =(L31-$F$23)/24 -> 1243.0229 | D31: Mirai | E31: XLE | G31: 0 | H31: TCCI | I31: JTDAAAAAXRA011657 | J31: =((L31+G31)/1.05)-G31 -> 54602.429 | K31: =((L31+G31)/1.05) -> 54602.429 | L31: 57332.55 | M31: 45434 | N31: 45413 | O31: 45573 | P31: 45566 | Q31: =(YEAR(O31) - YEAR(M31)) * 12 + MONTH(O31) - MONTH(M31) + 1 -> 6 | R31: =VLOOKUP(I31, [1]Fleet!$C:$V, 20, FALSE) -> Yes | S31: =VLOOKUP(I31, [1]Fleet!$C:$Q, 14, FALSE) -> 11600 | T31: 45627 | U31: 43697.45 | V31: =L31-(C31*Q31) -> 49874.413 | W31: =U31-V31 -> -6176.9625 | Z31: =Q31*C31 -> 7458.1375 | AA31: =(J31-$F$23)/24 -> 1129.2679 | AB31: =+AA31*Q31 -> 6775.6071 | AC31: =+Z31-AB31 -> 682.53036
B32: MY24 | C32: =(L32-$F$23)/24 -> 1243.0229 | D32: Mirai | E32: XLE | F32: Cannot locate BOS | G32: 0 | H32: TCCI | I32: JTDAAAAA5RA011663 | J32: =((L32+G32)/1.05)-G32 -> 54602.429 | K32: =((L32+G32)/1.05) -> 54602.429 | L32: 57332.55 | M32: 45435 | N32: 45413 | O32: 45596 | P32: 45566 | Q32: =(YEAR(O32) - YEAR(M32)) * 12 + MONTH(O32) - MONTH(M32) + 1 -> 6 | R32: =VLOOKUP(I32, [1]Fleet!$C:$V, 20, FALSE) -> No | S32: =VLOOKUP(I32, [1]Fleet!$C:$Q, 14, FALSE) -> 11411 | T32: 45627 | U32: 46471.36 | V32: =L32-(C32*Q32) -> 49874.413 | W32: =U32-V32 -> -3403.0525 | Z32: =Q32*C32 -> 7458.1375 | AA32: =(J32-$F$23)/24 -> 1129.2679 | AB32: =+AA32*Q32 -> 6775.6071 | AC32: =+Z32-AB32 -> 682.53036
D34: w/o iZEV | E34: RV | F34: 22300
B35: MY25 | C35: =(L35-$F$35)/24 -> 1073.2708 | D35: bZ4X | E35: LE FWD | F35: =F34 -> 22300 | G35: 0 | H35: TCCI | I35: JTMAAAAA1SA058324 | J35: =((L35+G35)/1.05)-G35 -> 45770 | K35: =((L35+G35)/1.05) -> 45770 | L35: 48058.5 | M35: 45715 | N35: 45689 | O35: =TODAY() -> 46106 | Q35: =(YEAR(O35) - YEAR(M35)) * 12 + MONTH(O35) - MONTH(M35) + 1 -> 14 | R35: =VLOOKUP(I35, [1]Fleet!$C:$V, 20, FALSE) -> No | S35: =VLOOKUP(I35, [1]Fleet!$C:$Q, 14, FALSE) -> 17875 | V35: =L35-(C35*Q35) -> 33032.708 | Z35: =Q35*C35 -> 15025.792 | AA35: =(J35-$F$35)/24 -> 977.91667 | AB35: =+AA35*Q35 -> 13690.833 | AC35: =+Z35-AB35 -> 1334.9583
B36: MY25 | C36: =(L36-$F$35)/24 -> 1073.2708 | D36: bZ4X | E36: LE FWD | G36: 0 | H36: TCCI | I36: JTMAAAAA3SA058289 | J36: =((L36+G36)/1.05)-G36 -> 45770 | K36: =((L36+G36)/1.05) -> 45770 | L36: 48058.5 | M36: 45715 | N36: 45689 | O36: =TODAY() -> 46106 | Q36: =(YEAR(O36) - YEAR(M36)) * 12 + MONTH(O36) - MONTH(M36) + 1 -> 14 | R36: =VLOOKUP(I36, [1]Fleet!$C:$V, 20, FALSE) -> No | S36: =VLOOKUP(I36, [1]Fleet!$C:$Q, 14, FALSE) -> 39793 | V36: =L36-(C36*Q36) -> 33032.708 | Z36: =Q36*C36 -> 15025.792 | AA36: =(J36-$F$35)/24 -> 977.91667 | AB36: =+AA36*Q36 -> 13690.833 | AC36: =+Z36-AB36 -> 1334.9583
B37: MY25 | C37: =(L37-$F$35)/24 -> 1073.2708 | D37: bZ4X | E37: LE FWD | G37: 0 | H37: TCCI | I37: JTMAAAAA8SA058403 | J37: =((L37+G37)/1.05)-G37 -> 45770 | K37: =((L37+G37)/1.05) -> 45770 | L37: 48058.5 | M37: 45715 | N37: 45689 | O37: =TODAY() -> 46106 | Q37: =(YEAR(O37) - YEAR(M37)) * 12 + MONTH(O37) - MONTH(M37) + 1 -> 14 | R37: =VLOOKUP(I37, [1]Fleet!$C:$V, 20, FALSE) -> No | S37: =VLOOKUP(I37, [1]Fleet!$C:$Q, 14, FALSE) -> 43151 | V37: =L37-(C37*Q37) -> 33032.708 | Z37: =Q37*C37 -> 15025.792 | AA37: =(J37-$F$35)/24 -> 977.91667 | AB37: =+AA37*Q37 -> 13690.833 | AC37: =+Z37-AB37 -> 1334.9583
B38: MY25 | C38: =(L38-$F$35)/24 -> 1073.2708 | D38: bZ4X | E38: LE FWD | G38: 0 | H38: TCCI | I38: JTMAAAAA8SA058188 | J38: =((L38+G38)/1.05)-G38 -> 45770 | K38: =((L38+G38)/1.05) -> 45770 | L38: 48058.5 | M38: 45709 | N38: 45689 | O38: =TODAY() -> 46106 | Q38: =(YEAR(O38) - YEAR(M38)) * 12 + MONTH(O38) - MONTH(M38) + 1 -> 14 | R38: =VLOOKUP(I38, [1]Fleet!$C:$V, 20, FALSE) -> No | S38: =VLOOKUP(I38, [1]Fleet!$C:$Q, 14, FALSE) -> 5389 | V38: =L38-(C38*Q38) -> 33032.708 | Z38: =Q38*C38 -> 15025.792 | AA38: =(J38-$F$35)/24 -> 977.91667 | AB38: =+AA38*Q38 -> 13690.833 | AC38: =+Z38-AB38 -> 1334.9583
B39: MY25 | C39: =(L39-$F$35)/24 -> 1073.2708 | D39: bZ4X | E39: LE FWD | G39: 0 | H39: TCCI | I39: JTMAAAAA4SA058141 | J39: =((L39+G39)/1.05)-G39 -> 45770 | K39: =((L39+G39)/1.05) -> 45770 | L39: 48058.5 | M39: 45712 | N39: 45689 | O39: =TODAY() -> 46106 | Q39: =(YEAR(O39) - YEAR(M39)) * 12 + MONTH(O39) - MONTH(M39) + 1 -> 14 | R39: =VLOOKUP(I39, [1]Fleet!$C:$V, 20, FALSE) -> No | S39: =VLOOKUP(I39, [1]Fleet!$C:$Q, 14, FALSE) -> 20080 | V39: =L39-(C39*Q39) -> 33032.708 | Z39: =Q39*C39 -> 15025.792 | AA39: =(J39-$F$35)/24 -> 977.91667 | AB39: =+AA39*Q39 -> 13690.833 | AC39: =+Z39-AB39 -> 1334.9583
B40: MY25 | C40: =(L40-$F$35)/24 -> 1073.2708 | D40: bZ4X | E40: LE FWD | G40: 0 | H40: TCCI | I40: JTMAAAAA7SA058201 | J40: =((L40+G42)/1.05)-G42 -> 45770 | K40: =((L40+G40)/1.05) -> 45770 | L40: 48058.5 | M40: 45713 | N40: 45689 | O40: =TODAY() -> 46106 | Q40: =(YEAR(O40) - YEAR(M40)) * 12 + MONTH(O40) - MONTH(M40) + 1 -> 14 | R40: =VLOOKUP(I40, [1]Fleet!$C:$V, 20, FALSE) -> No | S40: =VLOOKUP(I40, [1]Fleet!$C:$Q, 14, FALSE) -> 20118 | V40: =L40-(C40*Q40) -> 33032.708 | Z40: =Q40*C40 -> 15025.792 | AA40: =(J40-$F$35)/24 -> 977.91667 | AB40: =+AA40*Q40 -> 13690.833 | AC40: =+Z40-AB40 -> 1334.9583
B41: MY25 | C41: =(L41-$F$35)/24 -> 1073.2708 | D41: bZ4X | E41: LE FWD | G41: 0 | H41: TCCI | I41: JTMAAAAA1SA058341 | J41: =((L41+G59)/1.05)-G59 -> 45770 | K41: =((L41+G41)/1.05) -> 45770 | L41: 48058.5 | M41: 45731 | N41: 45717 | O41: =TODAY() -> 46106 | Q41: =(YEAR(O41) - YEAR(M41)) * 12 + MONTH(O41) - MONTH(M41) + 1 -> 13 | R41: =VLOOKUP(I41, [1]Fleet!$C:$V, 20, FALSE) -> No | S41: =VLOOKUP(I41, [1]Fleet!$C:$Q, 14, FALSE) -> 26812 | V41: =L41-(C41*Q41) -> 34105.979 | Z41: =Q41*C41 -> 13952.521 | AA41: =(J41-$F$35)/24 -> 977.91667 | AB41: =+AA41*Q41 -> 12712.917 | AC41: =+Z41-AB41 -> 1239.6042
D43: w/o iZEV | E43: RV | F43: 23000
B44: MY25 | C44: =(L44-$F$44)/24 -> 1064.7979 | D44: bZ4X | E44: LE AWD | F44: =F43 -> 23000 | G44: 0 | H44: TCCI | I44: JTMABACA1SA094718 | J44: =((L44+G44)/1.05)-G44 -> 46243 | K44: =((L44+G44)/1.05) -> 46243 | L44: 48555.15 | M44: 45708 | N44: 45689 | O44: =TODAY() -> 46106 | Q44: =(YEAR(O44) - YEAR(M44)) * 12 + MONTH(O44) - MONTH(M44) + 1 -> 14 | R44: =VLOOKUP(I44, [1]Fleet!$C:$V, 20, FALSE) -> No | S44: =VLOOKUP(I44, [1]Fleet!$C:$Q, 14, FALSE) -> 18765 | V44: =L44-(C44*Q44) -> 33647.979 | Z44: =Q44*C44 -> 14907.171 | AA44: =(J44-$F$44)/24 -> 968.45833 | AB44: =+AA44*Q44 -> 13558.417 | AC44: =+Z44-AB44 -> 1348.7542
B45: MY25 | C45: =(L45-$F$44)/24 -> 1064.7979 | D45: bZ4X | E45: LE AWD | G45: 0 | H45: TCCI | I45: JTMABACA0SA094807 | J45: =((L45+G45)/1.05)-G45 -> 46243 | K45: =((L45+G45)/1.05) -> 46243 | L45: 48555.15 | M45: 45720 | N45: 45717 | O45: =TODAY() -> 46106 | Q45: =(YEAR(O45) - YEAR(M45)) * 12 + MONTH(O45) - MONTH(M45) + 1 -> 13 | R45: =VLOOKUP(I45, [1]Fleet!$C:$V, 20, FALSE) -> No | S45: =VLOOKUP(I45, [1]Fleet!$C:$Q, 14, FALSE) -> 27085 | V45: =L45-(C45*Q45) -> 34712.777 | Z45: =Q45*C45 -> 13842.373 | AA45: =(J45-$F$44)/24 -> 968.45833 | AB45: =+AA45*Q45 -> 12589.958 | AC45: =+Z45-AB45 -> 1252.4146
B46: MY25 | C46: =(L46-$F$44)/24 -> 1064.7979 | D46: bZ4X | E46: LE AWD | G46: 0 | H46: TCCI | I46: JTMABACA7SA094917 | J46: =((L46+G46)/1.05)-G46 -> 46243 | K46: =((L46+G46)/1.05) -> 46243 | L46: 48555.15 | M46: 45708 | N46: 45689 | O46: =TODAY() -> 46106 | Q46: =(YEAR(O46) - YEAR(M46)) * 12 + MONTH(O46) - MONTH(M46) + 1 -> 14 | R46: =VLOOKUP(I46, [1]Fleet!$C:$V, 20, FALSE) -> No | S46: =VLOOKUP(I46, [1]Fleet!$C:$Q, 14, FALSE) -> 36169 | V46: =L46-(C46*Q46) -> 33647.979 | Z46: =Q46*C46 -> 14907.171 | AA46: =(J46-$F$44)/24 -> 968.45833 | AB46: =+AA46*Q46 -> 13558.417 | AC46: =+Z46-AB46 -> 1348.7542
B47: MY25 | C47: =(L47-$F$44)/24 -> 1064.7979 | D47: bZ4X | E47: LE AWD | G47: 0 | H47: TCCI | I47: JTMABACA3SA094817 | J47: =((L47+G47)/1.05)-G47 -> 46243 | K47: =((L47+G47)/1.05) -> 46243 | L47: 48555.15 | M47: 45715 | N47: 45689 | O47: =TODAY() -> 46106 | Q47: =(YEAR(O47) - YEAR(M47)) * 12 + MONTH(O47) - MONTH(M47) + 1 -> 14 | R47: =VLOOKUP(I47, [1]Fleet!$C:$V, 20, FALSE) -> No | S47: =VLOOKUP(I47, [1]Fleet!$C:$Q, 14, FALSE) -> 37844 | V47: =L47-(C47*Q47) -> 33647.979 | Z47: =Q47*C47 -> 14907.171 | AA47: =(J47-$F$44)/24 -> 968.45833 | AB47: =+AA47*Q47 -> 13558.417 | AC47: =+Z47-AB47 -> 1348.7542
B48: MY25 | C48: =(L48-$F$44)/24 -> 1064.7979 | D48: bZ4X | E48: LE AWD | G48: 0 | H48: TCCI | I48: JTMABACA8SA094988 | J48: =((L48+G48)/1.05)-G48 -> 46243 | K48: =((L48+G48)/1.05) -> 46243 | L48: 48555.15 | M48: 45715 | N48: 45689 | O48: =TODAY() -> 46106 | Q48: =(YEAR(O48) - YEAR(M48)) * 12 + MONTH(O48) - MONTH(M48) + 1 -> 14 | R48: =VLOOKUP(I48, [1]Fleet!$C:$V, 20, FALSE) -> No | S48: =VLOOKUP(I48, [1]Fleet!$C:$Q, 14, FALSE) -> 24994 | V48: =L48-(C48*Q48) -> 33647.979 | Z48: =Q48*C48 -> 14907.171 | AA48: =(J48-$F$44)/24 -> 968.45833 | AB48: =+AA48*Q48 -> 13558.417 | AC48: =+Z48-AB48 -> 1348.7542
B49: MY25 | C49: =(L49-$F$44)/24 -> 1064.7979 | D49: bZ4X | E49: LE AWD | G49: 0 | H49: TCCI | I49: JTMABACA8SA094733 | J49: =((L49+G49)/1.05)-G49 -> 46243 | K49: =((L49+G49)/1.05) -> 46243 | L49: 48555.15 | M49: 45709 | N49: 45689 | O49: =TODAY() -> 46106 | Q49: =(YEAR(O49) - YEAR(M49)) * 12 + MONTH(O49) - MONTH(M49) + 1 -> 14 | R49: =VLOOKUP(I49, [1]Fleet!$C:$V, 20, FALSE) -> No | S49: =VLOOKUP(I49, [1]Fleet!$C:$Q, 14, FALSE) -> 10729 | V49: =L49-(C49*Q49) -> 33647.979 | Z49: =Q49*C49 -> 14907.171 | AA49: =(J49-$F$44)/24 -> 968.45833 | AB49: =+AA49*Q49 -> 13558.417 | AC49: =+Z49-AB49 -> 1348.7542
B50: MY25 | C50: =(L50-$F$44)/24 -> 1064.7979 | D50: bZ4X | E50: LE AWD | G50: 0 | H50: TCCI | I50: JTMABACA3SA094722 | J50: =((L50+G50)/1.05)-G50 -> 46243 | K50: =((L50+G50)/1.05) -> 46243 | L50: 48555.15 | M50: 45716 | N50: 45689 | O50: =TODAY() -> 46106 | Q50: =(YEAR(O50) - YEAR(M50)) * 12 + MONTH(O50) - MONTH(M50) + 1 -> 14 | R50: =VLOOKUP(I50, [1]Fleet!$C:$V, 20, FALSE) -> No | S50: =VLOOKUP(I50, [1]Fleet!$C:$Q, 14, FALSE) -> 6580 | V50: =L50-(C50*Q50) -> 33647.979 | Z50: =Q50*C50 -> 14907.171 | AA50: =(J50-$F$44)/24 -> 968.45833 | AB50: =+AA50*Q50 -> 13558.417 | AC50: =+Z50-AB50 -> 1348.7542
B51: MY25 | C51: =(L51-$F$44)/24 -> 1064.7979 | D51: bZ4X | E51: LE AWD | G51: 0 | H51: TCCI | I51: JTMABACA4SA094891 | J51: =((L51+G58)/1.05)-G58 -> 46243 | K51: =((L51+G51)/1.05) -> 46243 | L51: 48555.15 | M51: 45731 | N51: 45717 | O51: =TODAY() -> 46106 | Q51: =(YEAR(O51) - YEAR(M51)) * 12 + MONTH(O51) - MONTH(M51) + 1 -> 13 | R51: =VLOOKUP(I51, [1]Fleet!$C:$V, 20, FALSE) -> No | S51: =VLOOKUP(I51, [1]Fleet!$C:$Q, 14, FALSE) -> 35324 | V51: =L51-(C51*Q51) -> 34712.777 | Z51: =Q51*C51 -> 13842.373 | AA51: =(J51-$F$44)/24 -> 968.45833 | AB51: =+AA51*Q51 -> 12589.958 | AC51: =+Z51-AB51 -> 1252.4146
D52: w/o iZEV | E52: RV | F52: 23000
B53: MY25 | C53: =(L53-F53)/24 -> 1073.9417 | D53: bZ4X | E53: LE AWD | F53: =F52 -> 23000 | G53: 0 | H53: TCCI | I53: JTMABACA8SA096921 | J53: =((L53+G65)/1.05)-G65 -> 46452 | K53: =((L53+G53)/1.05) -> 46452 | L53: 48774.6 | M53: 45733 | N53: 45717 | O53: =TODAY() -> 46106 | Q53: =(YEAR(O53) - YEAR(M53)) * 12 + MONTH(O53) - MONTH(M53) + 1 -> 13 | R53: =VLOOKUP(I53, [1]Fleet!$C:$V, 20, FALSE) -> No | S53: =VLOOKUP(I53, [1]Fleet!$C:$Q, 14, FALSE) -> 34507 | V53: =L53-(C53*Q53) -> 34813.358 | Z53: =Q53*C53 -> 13961.242 | AA53: =(J53-F53)/24 -> 977.16667 | AB53: =+AA53*Q53 -> 12703.167 | AC53: =+Z53-AB53 -> 1258.075
L55: w/ Tax | V55: G/L on Sale | Y55: Total Depreciation
K56: TOTAL | L56: =SUM(L5:L53) -> 1749396.1 | V56: bZ | W56: =SUM(W5:W20)+SUM(W35:W53) -> -31381.936 | X56: =SUM(X5:X20)+SUM(X35:X53) -> 1920 | Z56: =SUM(Z5:Z20)+SUM(Z35:Z53) -> 379819.86
K57: Total # of Vehicles | L57: {=COUNTA(_xlfn._xlws.FILTER(_xlfn.UNIQUE(I5:I53), _xlfn.UNIQUE(I5:I53) <> ""))} -> 35 | V57: Mirai | W57: =SUM(W23:W32) -> -5673.57 | X57: =SUM(X23:X32) -> 0 | Z57: =SUM(Z23:Z32) -> 64790.48
I59: JTMAAAAA4PA029083 | J59: =((L59+G59)/1.05)-G59 -> 42992.667 | K59: =((L59+G59)/1.05) -> 42992.667 | L59: 45142.3 | M59: 45284 | N59: 45261 | O59: 45708 | P59: 45689 | Q59: =(YEAR(O59) - YEAR(M59)) * 12 + MONTH(O59) - MONTH(M59) + 1 -> 15 | R59: =VLOOKUP(I59, [1]Fleet!$C:$V, 20, FALSE) -> Yes | S59: =VLOOKUP(I59, [1]Fleet!$C:$Q, 14, FALSE) -> 39566 | T59: 45748 | U59: 30990 | V59: =L59-(C59*Q59) -> 45142.3 | W59: =U59-V59 -> -14152.3 | Z59: =Q59*C59 -> 0 | AA59: =(J59-$F$4)/24 -> 541.36111 | AB59: =+AA59*Q59 -> 8120.4167 | AC59: =+Z59-AB59 -> -8120.4167
I60: JTMAAAAA0PA028495 | J60: =((L60+G60)/1.05)-G60 -> 42992.667 | K60: =((L60+G60)/1.05) -> 42992.667 | L60: 45142.3 | M60: 45284 | N60: 45261 | O60: 45708 | P60: 45689 | Q60: =(YEAR(O60) - YEAR(M60)) * 12 + MONTH(O60) - MONTH(M60) + 1 -> 15 | R60: =VLOOKUP(I60, [1]Fleet!$C:$V, 20, FALSE) -> No | S60: =VLOOKUP(I60, [1]Fleet!$C:$Q, 14, FALSE) -> 38739 | T60: 45717 | U60: 29490 | V60: =L60-(C60*Q60) -> 45142.3 | W60: =U60-V60 -> -15652.3 | Z60: =Q60*C60 -> 0 | AA60: =(J60-$F$4)/24 -> 541.36111 | AB60: =+AA60*Q60 -> 8120.4167 | AC60: =+Z60-AB60 -> -8120.4167
I61: JTMAAAAA9PA026597 | J61: =((L61+G61)/1.05)-G61 -> 42992.667 | K61: =((L61+G61)/1.05) -> 42992.667 | L61: 45142.3 | M61: 45284 | N61: 45261 | O61: 45708 | P61: 45689 | Q61: =(YEAR(O61) - YEAR(M61)) * 12 + MONTH(O61) - MONTH(M61) + 1 -> 15 | R61: =VLOOKUP(I61, [1]Fleet!$C:$V, 20, FALSE) -> Yes | S61: =VLOOKUP(I61, [1]Fleet!$C:$Q, 14, FALSE) -> 34435 | T61: 45748 | U61: 30490 | V61: =L61-(C61*Q61) -> 45142.3 | W61: =U61-V61 -> -14652.3 | Z61: =Q61*C61 -> 0 | AA61: =(J61-$F$4)/24 -> 541.36111 | AB61: =+AA61*Q61 -> 8120.4167 | AC61: =+Z61-AB61 -> -8120.4167
I62: JTMAAAAA7PA027683 | J62: =((L62+G62)/1.05)-G62 -> 42992.667 | K62: =((L62+G62)/1.05) -> 42992.667 | L62: 45142.3 | M62: 45284 | N62: 45261 | O62: =TODAY() -> 46106 | Q62: =(YEAR(O62) - YEAR(M62)) * 12 + MONTH(O62) - MONTH(M62) + 1 -> 28 | R62: =VLOOKUP(I62, [1]Fleet!$C:$V, 20, FALSE) -> Yes | S62: =VLOOKUP(I62, [1]Fleet!$C:$Q, 14, FALSE) -> 75774 | V62: =L62-(C62*Q62) -> 45142.3 | Z62: =Q62*C62 -> 0 | AA62: =(J62-$F$4)/24 -> 541.36111 | AB62: =+AA62*Q62 -> 15158.111 | AC62: =+Z62-AB62 -> -15158.111
I65: JTMABACA7PA044929 | J65: =((L65+G65)/1.05)-G65 -> 47739.971 | K65: =((L65+G65)/1.05) -> 47739.971 | L65: 50126.97 | M65: 45284 | N65: 45261 | O65: 45708 | P65: 45689 | Q65: =(YEAR(O65) - YEAR(M65)) * 12 + MONTH(O65) - MONTH(M65) + 1 -> 15 | R65: =VLOOKUP(I65, [1]Fleet!$C:$V, 20, FALSE) -> Yes | S65: =VLOOKUP(I65, [1]Fleet!$C:$Q, 14, FALSE) -> 24019 | T65: 45748 | U65: 38420 | V65: =L65-(C65*Q65) -> 50126.97 | W65: =U65-V65 -> -11706.97 | Z65: =Q65*C65 -> 0 | AA65: =(J65-$F$10)/24 -> 739.16548 | AB65: =+AA65*Q65 -> 11087.482 | AC65: =+Z65-AB65 -> -11087.482
I66: JTMABACA5PA045254 | J66: =((L66+G66)/1.05)-G66 -> 47739.971 | K66: =((L66+G66)/1.05) -> 47739.971 | L66: 50126.97 | M66: 45284 | N66: 45261 | O66: 45708 | P66: 45689 | Q66: =(YEAR(O66) - YEAR(M66)) * 12 + MONTH(O66) - MONTH(M66) + 1 -> 15 | R66: =VLOOKUP(I66, [1]Fleet!$C:$V, 20, FALSE) -> No | S66: =VLOOKUP(I66, [1]Fleet!$C:$Q, 14, FALSE) -> 39210 | T66: 45748 | U66: 35490 | V66: =L66-(C66*Q66) -> 50126.97 | W66: =U66-V66 -> -14636.97 | Z66: =Q66*C66 -> 0 | AA66: =(J66-$F$10)/24 -> 739.16548 | AB66: =+AA66*Q66 -> 11087.482 | AC66: =+Z66-AB66 -> -11087.482
I67: JTMABACA5PA045139 | J67: =((L67+G67)/1.05)-G67 -> 47739.971 | K67: =((L67+G67)/1.05) -> 47739.971 | L67: 50126.97 | M67: 45284 | N67: 45261 | O67: 45708 | P67: 45689 | Q67: =(YEAR(O67) - YEAR(M67)) * 12 + MONTH(O67) - MONTH(M67) + 1 -> 15 | R67: =VLOOKUP(I67, [1]Fleet!$C:$V, 20, FALSE) -> No | S67: =VLOOKUP(I67, [1]Fleet!$C:$Q, 14, FALSE) -> 47453 | T67: 45717 | U67: 33000 | V67: =L67-(C67*Q67) -> 50126.97 | W67: =U67-V67 -> -17126.97 | Z67: =Q67*C67 -> 0 | AA67: =(J67-$F$10)/24 -> 739.16548 | AB67: =+AA67*Q67 -> 11087.482 | AC67: =+Z67-AB67 -> -11087.482
I68: JTMABACA4PA045262 | J68: =((L68+G68)/1.05)-G68 -> 47739.971 | K68: =((L68+G68)/1.05) -> 47739.971 | L68: 50126.97 | M68: 45284 | N68: 45261 | O68: 45708 | P68: 45689 | Q68: =(YEAR(O68) - YEAR(M68)) * 12 + MONTH(O68) - MONTH(M68) + 1 -> 15 | R68: =VLOOKUP(I68, [1]Fleet!$C:$V, 20, FALSE) -> Yes | S68: =VLOOKUP(I68, [1]Fleet!$C:$Q, 14, FALSE) -> 38351 | T68: 45717 | U68: 34000 | V68: =L68-(C68*Q68) -> 50126.97 | W68: =U68-V68 -> -16126.97 | Z68: =Q68*C68 -> 0 | AA68: =(J68-$F$10)/24 -> 739.16548 | AB68: =+AA68*Q68 -> 11087.482 | AC68: =+Z68-AB68 -> -11087.482
I69: JTMABACA8PA042963 | J69: =((L69+G69)/1.05)-G69 -> 47739.971 | K69: =((L69+G69)/1.05) -> 47739.971 | L69: 50126.97 | M69: 45284 | N69: 45261 | O69: 45708 | P69: 45689 | Q69: =(YEAR(O69) - YEAR(M69)) * 12 + MONTH(O69) - MONTH(M69) + 1 -> 15 | R69: =VLOOKUP(I69, [1]Fleet!$C:$V, 20, FALSE) -> No | S69: =VLOOKUP(I69, [1]Fleet!$C:$Q, 14, FALSE) -> 32851 | T69: 45748 | U69: 35990 | V69: =L69-(C69*Q69) -> 50126.97 | W69: =U69-V69 -> -14136.97 | Z69: =Q69*C69 -> 0 | AA69: =(J69-$F$10)/24 -> 739.16548 | AB69: =+AA69*Q69 -> 11087.482 | AC69: =+Z69-AB69 -> -11087.482
I70: JTMABACA5PA045366 | J70: =((L70+G70)/1.05)-G70 -> 47739.971 | K70: =((L70+G70)/1.05) -> 47739.971 | L70: 50126.97 | M70: 45284 | N70: 45261 | O70: 45708 | P70: 45689 | Q70: =(YEAR(O70) - YEAR(M70)) * 12 + MONTH(O70) - MONTH(M70) + 1 -> 15 | R70: =VLOOKUP(I70, [1]Fleet!$C:$V, 20, FALSE) -> Yes | S70: =VLOOKUP(I70, [1]Fleet!$C:$Q, 14, FALSE) -> 31791 | T70: 45748 | U70: 35990 | V70: =L70-(C70*Q70) -> 50126.97 | W70: =U70-V70 -> -14136.97 | Z70: =Q70*C70 -> 0 | AA70: =(J70-$F$10)/24 -> 739.16548 | AB70: =+AA70*Q70 -> 11087.482 | AC70: =+Z70-AB70 -> -11087.482
I73: JTDAAAAA8PA008365 | J73: =((L73+G73)/1.05)-G73 -> 53847.429 | K73: =((L73+G73)/1.05) -> 53847.429 | L73: 56539.8 | M73: 45373 | N73: 45352 | O73: 45735 | P73: 45717 | Q73: =(YEAR(O73) - YEAR(M73)) * 12 + MONTH(O73) - MONTH(M73) + 1 -> 13 | R73: =VLOOKUP(I73, [1]Fleet!$C:$V, 20, FALSE) -> Yes | S73: =VLOOKUP(I73, [1]Fleet!$C:$Q, 14, FALSE) -> 20708 | V73: =L73-(C73*Q73) -> 56539.8 | Z73: =Q73*C73 -> 0 | AA73: =(J73-$F$18)/24 -> 2243.6429 | AB73: =+AA73*Q73 -> 29167.357 | AC73: =+Z73-AB73 -> -29167.357
I74: JTDAAAAA9PA008438 | J74: =((L74+G74)/1.05)-G74 -> 53847.429 | K74: =((L74+G74)/1.05) -> 53847.429 | L74: 56539.8 | M74: 45365 | N74: 45352 | O74: 45623 | P74: 45597 | Q74: =(YEAR(O74) - YEAR(M74)) * 12 + MONTH(O74) - MONTH(M74) + 1 -> 9 | R74: =VLOOKUP(I74, [1]Fleet!$C:$V, 20, FALSE) -> No | S74: =VLOOKUP(I74, [1]Fleet!$C:$Q, 14, FALSE) -> 182 | V74: =L74-(C74*Q74) -> 56539.8 | Z74: =Q74*C74 -> 0 | AA74: =(J74-$F$18)/24 -> 2243.6429 | AB74: =+AA74*Q74 -> 20192.786 | AC74: =+Z74-AB74 -> -20192.786
I75: JTDAAAAA3PA008371 | J75: =((L75+G75)/1.05)-G75 -> 53847.429 | K75: =((L75+G75)/1.05) -> 53847.429 | L75: 56539.8 | M75: 45376 | N75: 45352 | O75: 45623 | P75: 45597 | Q75: =(YEAR(O75) - YEAR(M75)) * 12 + MONTH(O75) - MONTH(M75) + 1 -> 9 | R75: =VLOOKUP(I75, [1]Fleet!$C:$V, 20, FALSE) -> No | S75: =VLOOKUP(I75, [1]Fleet!$C:$Q, 14, FALSE) -> 311 | V75: =L75-(C75*Q75) -> 56539.8 | Z75: =Q75*C75 -> 0 | AA75: =(J75-$F$18)/24 -> 2243.6429 | AB75: =+AA75*Q75 -> 20192.786 | AC75: =+Z75-AB75 -> -20192.786
I78: JTMAAAAAXRA050104 | J78: =((L78+G78)/1.05)-G78 -> 44782.095 | K78: =((L78+G78)/1.05) -> 44782.095 | L78: 47021.2 | M78: 45639 | N78: 45627 | O78: =TODAY() -> 46106 | Q78: =(YEAR(O78) - YEAR(M78)) * 12 + MONTH(O78) - MONTH(M78) + 1 -> 16 | R78: =VLOOKUP(I78, [1]Fleet!$C:$V, 20, FALSE) -> Yes | S78: =VLOOKUP(I78, [1]Fleet!$C:$Q, 14, FALSE) -> 22413 | V78: =L78-(C78*Q78) -> 47021.2 | Z78: =Q78*C78 -> 0 | AA78: =(J78-$F$23)/24 -> 720.0873 | AB78: =+AA78*Q78 -> 11521.397 | AC78: =+Z78-AB78 -> -11521.397
I79: JTMAAAAA8RA050148 | J79: =((L79+G79)/1.05)-G79 -> 44782.095 | K79: =((L79+G79)/1.05) -> 44782.095 | L79: 47021.2 | M79: 45643 | N79: 45627 | O79: =TODAY() -> 46106 | Q79: =(YEAR(O79) - YEAR(M79)) * 12 + MONTH(O79) - MONTH(M79) + 1 -> 16 | R79: =VLOOKUP(I79, [1]Fleet!$C:$V, 20, FALSE) -> No | S79: =VLOOKUP(I79, [1]Fleet!$C:$Q, 14, FALSE) -> 30800 | V79: =L79-(C79*Q79) -> 47021.2 | Z79: =Q79*C79 -> 0 | AA79: =(J79-$F$23)/24 -> 720.0873 | AB79: =+AA79*Q79 -> 11521.397 | AC79: =+Z79-AB79 -> -11521.397
I80: JTMAAAAA5RA050253 | J80: =((L80+G80)/1.05)-G80 -> 44782.095 | K80: =((L80+G80)/1.05) -> 44782.095 | L80: 47021.2 | M80: 45643 | N80: 45627 | O80: =TODAY() -> 46106 | Q80: =(YEAR(O80) - YEAR(M80)) * 12 + MONTH(O80) - MONTH(M80) + 1 -> 16 | R80: =VLOOKUP(I80, [1]Fleet!$C:$V, 20, FALSE) -> No | S80: =VLOOKUP(I80, [1]Fleet!$C:$Q, 14, FALSE) -> 30932 | V80: =L80-(C80*Q80) -> 47021.2 | Z80: =Q80*C80 -> 0 | AA80: =(J80-$F$23)/24 -> 720.0873 | AB80: =+AA80*Q80 -> 11521.397 | AC80: =+Z80-AB80 -> -11521.397
I81: JTMAAAAA5RA050334 | J81: =((L81+G81)/1.05)-G81 -> 44782.095 | K81: =((L81+G81)/1.05) -> 44782.095 | L81: 47021.2 | M81: 45643 | N81: 45627 | O81: =TODAY() -> 46106 | Q81: =(YEAR(O81) - YEAR(M81)) * 12 + MONTH(O81) - MONTH(M81) + 1 -> 16 | R81: =VLOOKUP(I81, [1]Fleet!$C:$V, 20, FALSE) -> No | S81: =VLOOKUP(I81, [1]Fleet!$C:$Q, 14, FALSE) -> 36433 | V81: =L81-(C81*Q81) -> 47021.2 | Z81: =Q81*C81 -> 0 | AA81: =(J81-$F$23)/24 -> 720.0873 | AB81: =+AA81*Q81 -> 11521.397 | AC81: =+Z81-AB81 -> -11521.397
I82: JTMAAAAA6RA050388 | J82: =((L82+G82)/1.05)-G82 -> 44782.095 | K82: =((L82+G82)/1.05) -> 44782.095 | L82: 47021.2 | M82: 45643 | N82: 45627 | O82: =TODAY() -> 46106 | Q82: =(YEAR(O82) - YEAR(M82)) * 12 + MONTH(O82) - MONTH(M82) + 1 -> 16 | R82: =VLOOKUP(I82, [1]Fleet!$C:$V, 20, FALSE) -> No | S82: =VLOOKUP(I82, [1]Fleet!$C:$Q, 14, FALSE) -> 38373 | V82: =L82-(C82*Q82) -> 47021.2 | Z82: =Q82*C82 -> 0 | AA82: =(J82-$F$23)/24 -> 720.0873 | AB82: =+AA82*Q82 -> 11521.397 | AC82: =+Z82-AB82 -> -11521.397
I83: JTMAAAAA5RA050706 | J83: =((L83+G83)/1.05)-G83 -> 44782.095 | K83: =((L83+G83)/1.05) -> 44782.095 | L83: 47021.2 | M83: 45643 | N83: 45627 | O83: =TODAY() -> 46106 | Q83: =(YEAR(O83) - YEAR(M83)) * 12 + MONTH(O83) - MONTH(M83) + 1 -> 16 | R83: =VLOOKUP(I83, [1]Fleet!$C:$V, 20, FALSE) -> No | S83: =VLOOKUP(I83, [1]Fleet!$C:$Q, 14, FALSE) -> 47646 | V83: =L83-(C83*Q83) -> 47021.2 | Z83: =Q83*C83 -> 0 | AA83: =(J83-$F$23)/24 -> 720.0873 | AB83: =+AA83*Q83 -> 11521.397 | AC83: =+Z83-AB83 -> -11521.397
I84: JTMAAAAA8RA050716 | J84: =((L84+G84)/1.05)-G84 -> 44782.095 | K84: =((L84+G84)/1.05) -> 44782.095 | L84: 47021.2 | M84: 45643 | N84: 45627 | O84: =TODAY() -> 46106 | Q84: =(YEAR(O84) - YEAR(M84)) * 12 + MONTH(O84) - MONTH(M84) + 1 -> 16 | R84: =VLOOKUP(I84, [1]Fleet!$C:$V, 20, FALSE) -> No | S84: =VLOOKUP(I84, [1]Fleet!$C:$Q, 14, FALSE) -> 32147 | V84: =L84-(C84*Q84) -> 47021.2 | Z84: =Q84*C84 -> 0 | AA84: =(J84-$F$23)/24 -> 720.0873 | AB84: =+AA84*Q84 -> 11521.397 | AC84: =+Z84-AB84 -> -11521.397
I85: JTMAAAAA1RA050816 | J85: =((L85+G85)/1.05)-G85 -> 44782.095 | K85: =((L85+G85)/1.05) -> 44782.095 | L85: 47021.2 | M85: 45639 | N85: 45627 | O85: =TODAY() -> 46106 | Q85: =(YEAR(O85) - YEAR(M85)) * 12 + MONTH(O85) - MONTH(M85) + 1 -> 16 | R85: =VLOOKUP(I85, [1]Fleet!$C:$V, 20, FALSE) -> Yes | S85: =VLOOKUP(I85, [1]Fleet!$C:$Q, 14, FALSE) -> 20630 | V85: =L85-(C85*Q85) -> 47021.2 | Z85: =Q85*C85 -> 0 | AA85: =(J85-$F$23)/24 -> 720.0873 | AB85: =+AA85*Q85 -> 11521.397 | AC85: =+Z85-AB85 -> -11521.397
I86: JTMAAAAA0RA050998 | J86: =((L86+G86)/1.05)-G86 -> 44782.095 | K86: =((L86+G86)/1.05) -> 44782.095 | L86: 47021.2 | M86: 45639 | N86: 45627 | O86: =TODAY() -> 46106 | Q86: =(YEAR(O86) - YEAR(M86)) * 12 + MONTH(O86) - MONTH(M86) + 1 -> 16 | R86: =VLOOKUP(I86, [1]Fleet!$C:$V, 20, FALSE) -> No | S86: =VLOOKUP(I86, [1]Fleet!$C:$Q, 14, FALSE) -> 26034 | V86: =L86-(C86*Q86) -> 47021.2 | Z86: =Q86*C86 -> 0 | AA86: =(J86-$F$23)/24 -> 720.0873 | AB86: =+AA86*Q86 -> 11521.397 | AC86: =+Z86-AB86 -> -11521.397
I87: JTMAAAAA4RA051104 | J87: =((L87+G87)/1.05)-G87 -> 44782.095 | K87: =((L87+G87)/1.05) -> 44782.095 | L87: 47021.2 | M87: 45639 | N87: 45627 | O87: =TODAY() -> 46106 | Q87: =(YEAR(O87) - YEAR(M87)) * 12 + MONTH(O87) - MONTH(M87) + 1 -> 16 | R87: =VLOOKUP(I87, [1]Fleet!$C:$V, 20, FALSE) -> No | S87: =VLOOKUP(I87, [1]Fleet!$C:$Q, 14, FALSE) -> 36906 | V87: =L87-(C87*Q87) -> 47021.2 | Z87: =Q87*C87 -> 0 | AA87: =(J87-$F$23)/24 -> 720.0873 | AB87: =+AA87*Q87 -> 11521.397 | AC87: =+Z87-AB87 -> -11521.397
I88: JTMAAAAA5RA051242 | J88: =((L88+G88)/1.05)-G88 -> 44782.095 | K88: =((L88+G88)/1.05) -> 44782.095 | L88: 47021.2 | M88: 45639 | N88: 45627 | O88: =TODAY() -> 46106 | Q88: =(YEAR(O88) - YEAR(M88)) * 12 + MONTH(O88) - MONTH(M88) + 1 -> 16 | R88: =VLOOKUP(I88, [1]Fleet!$C:$V, 20, FALSE) -> No | S88: =VLOOKUP(I88, [1]Fleet!$C:$Q, 14, FALSE) -> 22055 | V88: =L88-(C88*Q88) -> 47021.2 | Z88: =Q88*C88 -> 0 | AA88: =(J88-$F$23)/24 -> 720.0873 | AB88: =+AA88*Q88 -> 11521.397 | AC88: =+Z88-AB88 -> -11521.397
I89: JTMAAAAA3RA051224 | J89: =((L89+G89)/1.05)-G89 -> 44782.095 | K89: =((L89+G89)/1.05) -> 44782.095 | L89: 47021.2 | M89: 45639 | N89: 45627 | O89: =TODAY() -> 46106 | Q89: =(YEAR(O89) - YEAR(M89)) * 12 + MONTH(O89) - MONTH(M89) + 1 -> 16 | R89: =VLOOKUP(I89, [1]Fleet!$C:$V, 20, FALSE) -> No | S89: =VLOOKUP(I89, [1]Fleet!$C:$Q, 14, FALSE) -> 29987 | V89: =L89-(C89*Q89) -> 47021.2 | Z89: =Q89*C89 -> 0 | AA89: =(J89-$F$23)/24 -> 720.0873 | AB89: =+AA89*Q89 -> 11521.397 | AC89: =+Z89-AB89 -> -11521.397
... I104: JTMAAAAA2RA050565 | J104: =((L104+G104)/1.05)-G104 -> 44782.095 | K104: =((L104+G104)/1.05) -> 44782.095 | L104: 47021.2 | M104: 45639 | N104: 45627 | O104: =TODAY() -> 46106 | Q104: =(YEAR(O104) - YEAR(M104)) * 12 + MONTH(O104) - MONTH(M104) + 1 -> 16 | R104: =VLOOKUP(I104, [1]Fleet!$C:$V, 20, FALSE) -> No | S104: =VLOOKUP(I104, [1]Fleet!$C:$Q, 14, FALSE) -> 48386 | V104: =L104-(C104*Q104) -> 47021.2 | Z104: =Q104*C104 -> 0 | AA104: =(J104-$F$23)/24 -> 720.0873 | AB104: =+AA104*Q104 -> 11521.397 | AC104: =+Z104-AB104 -> -11521.397
I107: JTDAAAAAXRA011691 | J107: =((L107+G107)/1.05)-G107 -> 49470.724 | K107: =((L107+G107)/1.05) -> 49470.724 | L107: 51944.26 | M107: 45559 | N107: 45536 | O107: 45708 | P107: 45689 | Q107: =(YEAR(O107) - YEAR(M107)) * 12 + MONTH(O107) - MONTH(M107) + 1 -> 6 | R107: =VLOOKUP(I107, [1]Fleet!$C:$V, 20, FALSE) -> No | S107: =VLOOKUP(I107, [1]Fleet!$C:$Q, 14, FALSE) -> 38 | T107: 45748 | U107: 52763 | V107: =L107-(C107*Q107) -> 51944.26 | W107: =U107-V107 -> 818.74 | Z107: =Q107*C107 -> 0 | AA107: =(J107-$F$52)/24 -> 1102.9468 | AB107: =+AA107*Q107 -> 6617.681 | AC107: =+Z107-AB107 -> -6617.681
I109: JTDAAAAA8RA011754 | J109: =((L109+G109)/1.05)-G109 -> 49453.095 | K109: =((L109+G109)/1.05) -> 49453.095 | L109: 51925.75 | M109: 45646 | N109: 45627 | O109: =TODAY() -> 46106 | Q109: =(YEAR(O109) - YEAR(M109)) * 12 + MONTH(O109) - MONTH(M109) + 1 -> 16 | R109: =VLOOKUP(I109, [1]Fleet!$C:$V, 20, FALSE) -> No | S109: =VLOOKUP(I109, [1]Fleet!$C:$Q, 14, FALSE) -> 1250 | V109: =L109-(C109*Q109) -> 51925.75 | Z109: =Q109*C109 -> 0 | AA109: =(J109-$F$54)/24 -> 2060.5456 | AB109: =+AA109*Q109 -> 32968.73 | AC109: =+Z109-AB109 -> -32968.73
I110: JTDAAAAA0RA011764 | J110: =((L110+G110)/1.05)-G110 -> 49453.095 | K110: =((L110+G110)/1.05) -> 49453.095 | L110: 51925.75 | M110: 45646 | N110: 45627 | O110: =TODAY() -> 46106 | Q110: =(YEAR(O110) - YEAR(M110)) * 12 + MONTH(O110) - MONTH(M110) + 1 -> 16 | R110: =VLOOKUP(I110, [1]Fleet!$C:$V, 20, FALSE) -> No | S110: =VLOOKUP(I110, [1]Fleet!$C:$Q, 14, FALSE) -> 12100 | V110: =L110-(C110*Q110) -> 51925.75 | Z110: =Q110*C110 -> 0 | AA110: =(J110-$F$54)/24 -> 2060.5456 | AB110: =+AA110*Q110 -> 32968.73 | AC110: =+Z110-AB110 -> -32968.73
I111: JTDAAAAAXRA011786 | J111: =((L111+G111)/1.05)-G111 -> 49453.095 | K111: =((L111+G111)/1.05) -> 49453.095 | L111: 51925.75 | M111: 45644 | N111: 45627 | O111: =TODAY() -> 46106 | Q111: =(YEAR(O111) - YEAR(M111)) * 12 + MONTH(O111) - MONTH(M111) + 1 -> 16 | R111: =VLOOKUP(I111, [1]Fleet!$C:$V, 20, FALSE) -> No | S111: =VLOOKUP(I111, [1]Fleet!$C:$Q, 14, FALSE) -> 13194 | V111: =L111-(C111*Q111) -> 51925.75 | Z111: =Q111*C111 -> 0 | AA111: =(J111-$F$54)/24 -> 2060.5456 | AB111: =+AA111*Q111 -> 32968.73 | AC111: =+Z111-AB111 -> -32968.73
I112: JTDAAAAA5RA011789 | J112: =((L112+G112)/1.05)-G112 -> 49453.095 | K112: =((L112+G112)/1.05) -> 49453.095 | L112: 51925.75 | M112: 45644 | N112: 45627 | O112: =TODAY() -> 46106 | Q112: =(YEAR(O112) - YEAR(M112)) * 12 + MONTH(O112) - MONTH(M112) + 1 -> 16 | R112: =VLOOKUP(I112, [1]Fleet!$C:$V, 20, FALSE) -> No | S112: =VLOOKUP(I112, [1]Fleet!$C:$Q, 14, FALSE) -> 5670 | V112: =L112-(C112*Q112) -> 51925.75 | Z112: =Q112*C112 -> 0 | AA112: =(J112-$F$54)/24 -> 2060.5456 | AB112: =+AA112*Q112 -> 32968.73 | AC112: =+Z112-AB112 -> -32968.73
I113: JTDAAAAA4RA011766 | J113: =((L113+G113)/1.05)-G113 -> 49453.095 | K113: =((L113+G113)/1.05) -> 49453.095 | L113: 51925.75 | M113: 45646 | N113: 45627 | O113: =TODAY() -> 46106 | Q113: =(YEAR(O113) - YEAR(M113)) * 12 + MONTH(O113) - MONTH(M113) + 1 -> 16 | R113: =VLOOKUP(I113, [1]Fleet!$C:$V, 20, FALSE) -> No | S113: =VLOOKUP(I113, [1]Fleet!$C:$Q, 14, FALSE) -> 11241 | V113: =L113-(C113*Q113) -> 51925.75 | Z113: =Q113*C113 -> 0 | AA113: =(J113-$F$54)/24 -> 2060.5456 | AB113: =+AA113*Q113 -> 32968.73 | AC113: =+Z113-AB113 -> -32968.73
I116: JTDAAAAA0RA011490 | J116: =((L116+G116)/1.05)-G116 -> 53847.429 | K116: =((L116+G116)/1.05) -> 53847.429 | L116: 56539.8 | M116: 45379 | N116: 45352 | O116: 45567 | P116: 45566 | Q116: =(YEAR(O116) - YEAR(M116)) * 12 + MONTH(O116) - MONTH(M116) + 1 -> 8 | R116: =VLOOKUP(I116, [1]Fleet!$C:$V, 20, FALSE) -> Yes | S116: =VLOOKUP(I116, [1]Fleet!$C:$Q, 14, FALSE) -> 13504 | T116: 45627 | U116: 45797.68 | V116: =L116-(C116*Q116) -> 56539.8 | W116: =U116-V116 -> -10742.12 | Z116: =Q116*C116 -> 0 | AA116: =(J116-$F$61)/24 -> 2243.6429 | AB116: =+AA116*Q116 -> 17949.143 | AC116: =+Z116-AB116 -> -17949.143
I117: JTDAAAAA7RA011566 | J117: =((L117+G117)/1.05)-G117 -> 53847.429 | K117: =((L117+G117)/1.05) -> 53847.429 | L117: 56539.8 | M117: 45376 | N117: 45352 | O117: 45596 | P117: 45566 | Q117: =(YEAR(O117) - YEAR(M117)) * 12 + MONTH(O117) - MONTH(M117) + 1 -> 8 | R117: =VLOOKUP(I117, [1]Fleet!$C:$V, 20, FALSE) -> No | S117: =VLOOKUP(I117, [1]Fleet!$C:$Q, 14, FALSE) -> 20576 | T117: 45627 | U117: 46141.6 | V117: =L117-(C117*Q117) -> 56539.8 | W117: =U117-V117 -> -10398.2 | Z117: =Q117*C117 -> 0 | AA117: =(J117-$F$61)/24 -> 2243.6429 | AB117: =+AA117*Q117 -> 17949.143 | AC117: =+Z117-AB117 -> -17949.143

Sheet data
A1: Vehicle ID | B1: VIN | C1: Plate Number | D1: Model | E1: MY | F1: Trim | G1: Colour | H1: Onboard date | I1: DLR Name | J1: Ownership | K1: Odometer 3_19_26 | L1: Latest Rent End | M1: Status | N1: Status 3_19_26 | O1: Purchase price | P1: Total Dep | Q1: Price to BE
A2: 44 | B2: JTDAAAAA8PA008365 | C2: OB-VN545G | D2: Mirai | E2: 2023 | F2: XLE | G2: Supersonic Red | H2: 45448 | I2: OpenRoad Toyota Richmond | J2: TCI | K2: #N/A | L2: 45754.585 | M2: Offboarded | N2: #N/A
A3: 45 | B3: JTDAAAAA0RA011490 | C3: OB-VN534G | D3: Mirai | E3: 2024 | F3: XLE | G3: Oxygen White | H3: 45448 | I3: OpenRoad Toyota Richmond | J3: TCI | K3: #N/A | L3: 45533.687 | M3: Sold | N3: #N/A
A4: 46 | B4: JTDAAAAA9PA008438 | C4: OB-VN546G | D4: Mirai | E4: 2023 | F4: XLE | G4: Oxygen White | H4: 45448 | I4: Westminster Toyota | J4: TCI | K4: #N/A | L4: 45622.612 | M4: Offboarded | N4: #N/A
A5: 47 | B5: JTDAAAAA3PA008371 | C5: OB-VN541G | D5: Mirai | E5: 2023 | F5: XLE | G5: Hydro Blue | H5: 45448 | I5: Destination Toyota Burnaby | J5: TCI | K5: #N/A | L5: 45622.613 | M5: Offboarded | N5: #N/A
A6: 48 | B6: JTDAAAAA7RA011566 | C6: OB-VN543G | D6: Mirai | E6: 2024 | F6: XLE | G6: Oxygen White | H6: 45448 | I6: Destination Toyota Burnaby | J6: TCI | K6: #N/A | L6: 45609.695 | M6: Sold | N6: #N/A
A7: 49 | B7: JTDAAAAAXRA011657 | C7: OB-VX143W | D7: Mirai | E7: 2024 | F7: XLE | G7: Oxygen White | H7: 45448 | I7: Destination Toyota Burnaby | J7: TCCI | K7: #N/A | L7: 45523.507 | M7: Sold | N7: #N/A
A8: 50 | B8: JTDAAAAA3RA011645 | C8: OB-VX105W | D8: Mirai | E8: 2024 | F8: XLE | G8: Oxygen White | H8: 45448 | I8: Westminster Toyota | J8: TCCI | K8: #N/A | L8: 45499.951 | M8: Sold | N8: #N/A
A9: 51 | B9: JTDAAAAA5RA011663 | C9: OB-VX104W | D9: Mirai | E9: 2024 | F9: XLE | G9: Oxygen White | H9: 45448 | I9: Westminster Toyota | J9: TCCI | K9: #N/A | L9: 45520.665 | M9: Sold | N9: #N/A
A10: 52 | B10: JTDAAAAA2RA011684 | C10: OB-VX124W | D10: Mirai | E10: 2024 | F10: XLE | G10: Oxygen White | H10: 45448 | I10: Westminster Toyota | J10: TCCI | K10: #N/A | L10: 45533.119 | M10: Sold | N10: #N/A
A11: 53 | B11: JTDAAAAA7RA011633 | C11: OB-VX146W | D11: Mirai | E11: 2024 | F11: XLE | G11: Oxygen White | H11: 45453 | I11: OpenRoad Toyota Richmond | J11: TCCI | K11: #N/A | L11: 45592.505 | M11: Sold | N11: #N/A
A12: 62 | B12: JTDAAAAAXRA011691 | C12: OB-VN534G | D12: Mirai | E12: 2024 | F12: XLE | G12: Oxygen White | H12: 45636 | I12: OpenRoad Toyota Richmond | J12: TCI | K12: #N/A | M12: Sold | N12: #N/A
A13: 63 | B13: JTDAAAAA6RA011705 | C13: OB2-VX105W | D13: Mirai | E13: 2024 | F13: XLE | G13: Oxygen White | H13: 45622 | I13: Westminster Toyota | J13: TCCI | K13: #N/A | M13: Sold | N13: #N/A
A14: 64 | B14: JTDAAAAA7RA011714 | C14: OB2-VX104W | D14: Mirai | E14: 2024 | F14: XLE | G14: Oxygen White | H14: 45622 | I14: Westminster Toyota | J14: TCCI | K14: #N/A | L14: 45722.854 | M14: Sold | N14: #N/A
A15: 65 | B15: JTDAAAAAXRA011724 | C15: OB2-VX124W | D15: Mirai | E15: 2024 | F15: XLE | G15: Oxygen White | H15: 45622 | I15: Westminster Toyota | J15: TCCI | K15: #N/A | L15: 45740.553 | M15: Sold | N15: #N/A
A16: 66 | B16: JTDAAAAAXRA011741 | C16: OB2-VX143W | D16: Mirai | E16: 2024 | F16: XLE | G16: Oxygen White | H16: 45636 | I16: Destination Toyota Burnaby | J16: TCCI | K16: #N/A | L16: 45726.577 | M16: Sold | N16: #N/A
A17: 103 | B17: JTDAAAAA8RA011754 | C17: WW595B | D17: Mirai | E17: 2024 | F17: XLE | G17: Oxygen White | H17: 45768 | I17: OpenRoad Toyota Richmond | J17: TCI | K17: 8181 | L17: 45779.501 | M17: Onboarded | N17: active | O17: =+VLOOKUP(B17,'Dep TCCI'!$I$3:$AC$117,2,FALSE) -> 49453.095 | P17: 22642.841 | Q17: =+O17-P17 -> 26810.254
A18: 104 | B18: JTDAAAAA0RA011764 | C18: WW597B | D18: Mirai | E18: 2024 | F18: XLE | H18: 12/31/1899 | I18: OpenRoad Toyota Richmond | J18: TCI | K18: 15356 | L18: 46059.069 | M18: Onboarded | N18: inactive | O18: =+VLOOKUP(B18,'Dep TCCI'!$I$3:$AC$117,2,FALSE) -> 49453.095 | P18: 22642.841 | Q18: =+O18-P18 -> 26810.254
A19: 109 | B19: JTDAAAAAXRA011786 | C19: WW591B | D19: Mirai | E19: 2024 | F19: XLE | G19: Oxygen White | H19: 45768 | I19: Destination Toyota Burnaby | J19: TCI | K19: 13244 | L19: 45967.629 | M19: Onboarded | N19: inactive | O19: =+VLOOKUP(B19,'Dep TCCI'!$I$3:$AC$117,2,FALSE) -> 49453.095 | P19: 22642.841 | Q19: =+O19-P19 -> 26810.254
A20: 110 | B20: JTDAAAAA5RA011789 | C20: WW593B | D20: Mirai | E20: 2024 | F20: XLE | G20: Oxygen White | H20: 45768 | I20: Destination Toyota Burnaby | J20: TCI | K20: 6062 | L20: 45911.555 | M20: Onboarded | N20: inactive | O20: =+VLOOKUP(B20,'Dep TCCI'!$I$3:$AC$117,2,FALSE) -> 49453.095 | P20: 22642.841 | Q20: =+O20-P20 -> 26810.254
A21: 111 | B21: JTDAAAAA4RA011766 | C21: VN543G | D21: Mirai | E21: 2024 | F21: XLE | G21: Oxygen White | H21: 45768 | I21: Westminster Toyota | J21: TCI | K21: 17584 | L21: 46027.451 | M21: Onboarded | N21: inactive | O21: =+VLOOKUP(B21,'Dep TCCI'!$I$3:$AC$117,2,FALSE) -> 49453.095 | P21: 22642.841 | Q21: =+O21-P21 -> 26810.254
A22: 24 | B22: JTMABACA5PA045254 | C22: OB-VC871J | D22: bZ4X | E22: 2023 | F22: XLE AWD | G22: Wind Chill Pearl | H22: 45328 | I22: OpenRoad Toyota Richmond | J22: TCI | K22: #N/A | L22: 45658.569 | M22: Offboarded | N22: #N/A
A23: 25 | B23: JTMAAAAA4PA029083 | C23: OB-VC872J | D23: bZ4X | E23: 2023 | F23: LE | G23: Wind Chill Pearl | H23: 45328 | I23: OpenRoad Toyota Richmond | J23: TCI | K23: #N/A | L23: 45705.458 | M23: Offboarded | N23: #N/A
A24: 26 | B24: JTMAAAAA8PA028907 | C24: OB-VC862J | D24: bZ4X | E24: 2023 | F24: LE | G24: Wind Chill Pearl | H24: 45328 | I24: OpenRoad Toyota Richmond | J24: TCCI | K24: #N/A | L24: 45677.443 | M24: Offboarded | N24: #N/A
A25: 27 | B25: JTMABACA7PA044929 | C25: OB-VC867J | D25: bZ4X | E25: 2023 | F25: XLE AWD | G25: Element Silver | H25: 45328 | I25: OpenRoad Toyota Richmond | J25: TCI | K25: #N/A | L25: 45600.012 | M25: Offboarded | N25: #N/A
A26: 28 | B26: JTMABACA9PA044818 | C26: VC861J | D26: bZ4X | E26: 2023 | F26: XLE AWD | G26: Wind Chill Pearl | H26: 45328 | I26: OpenRoad Toyota Richmond | J26: TCCI | K26: 53717 | L26: 46043.533 | M26: Onboarded | N26: active | O26: =+VLOOKUP(B26,'Dep TCCI'!$I$3:$AC$117,2,FALSE) -> 47359.019 | P26: 22642.841 | Q26: =+O26-P26 -> 24716.178
A27: 29 | B27: JTMAAAAA2PA027333 | C27: VC857J | D27: bZ4X | E27: 2023 | F27: LE | G27: Element Silver | H27: 45328 | I27: Jim Pattison Toyota Surrey | J27: TCCI | K27: 100170 | L27: 46051.516 | M27: Onboarded | N27: inactive | O27: =+VLOOKUP(B27,'Dep TCCI'!$I$3:$AC$117,2,FALSE) -> 42611.714 | P27: =+VLOOKUP(B27,'Dep TCCI'!$I$3:$AC$117,20,FALSE) -> 14713.667 | Q27: =+O27-P27 -> 27898.048
A28: 30 | B28: JTMAAAAA6PA023415 | C28: VC859J | D28: bZ4X | E28: 2023 | F28: LE | G28: Element Silver | H28: 45328 | I28: Jim Pattison Toyota Surrey | J28: TCCI | K28: 45554 | L28: 45736.482 | M28: Offboarded | N28: inactive
A29: 31 | B29: JTMABACA5PA045528 | C29: VC852J | D29: bZ4X | E29: 2023 | F29: XLE AWD | G29: Element Silver | H29: 45328 | I29: Jim Pattison Toyota Surrey | J29: TCCI | K29: 35432 | L29: 45737.942 | M29: Offboarded | N29: inactive
A30: 32 | B30: JTMABACA7PA042856 | C30: VC853J | D30: bZ4X | E30: 2023 | F30: XLE AWD | G30: Heavy Metal | H30: 45328 | I30: Jim Pattison Toyota Surrey | J30: TCCI | K30: 41930 | L30: 45770.657 | M30: Offboarded | N30: inactive
A31: 33 | B31: JTMABACA7PA046096 | C31: VC850J | D31: bZ4X | E31: 2023 | F31: XLE AWD | G31: Wind Chill Pearl | H31: 45328 | I31: Jim Pattison Toyota Surrey | J31: TCCI | K31: 59451 | L31: 45757.877 | M31: Offboarded | N31: inactive
A32: 34 | B32: JTMAAAAA7PA027683 | C32: TJ719P | D32: bZ4X | E32: 2023 | F32: LE | G32: Wind Chill Pearl | H32: 45328 | I32: Westminster Toyota | J32: TCI | K32: 83001 | L32: 45988.592 | M32: Onboarded | N32: inactive | O32: =+VLOOKUP(B32,'Dep TCCI'!$I$3:$AC$117,2,FALSE) -> 42992.667 | P32: =+VLOOKUP(B32,'Dep TCCI'!$I$3:$AC$117,20,FALSE) -> 15158.111 | Q32: =+O32-P32 -> 27834.556
A33: 35 | B33: JTMAAAAA9PA026597 | C33: OB-SL658D | D33: bZ4X | E33: 2023 | F33: LE | G33: Black | H33: 45328 | I33: Westminster Toyota | J33: TCI | K33: #N/A | L33: 45688.653 | M33: Offboarded | N33: #N/A
A34: 36 | B34: JTMABACA5PA045366 | C34: OB-TJ720P | D34: bZ4X | E34: 2023 | F34: XLE AWD | G34: Wind Chill Pearl | H34: 45328 | I34: Westminster Toyota | J34: TCI | K34: #N/A | L34: 45650.641 | M34: Offboarded | N34: #N/A
A35: 37 | B35: JTMABACA8PA042963 | C35: OB-VC837J | D35: bZ4X | E35: 2023 | F35: XLE AWD | G35: Heavy Metal | H35: 45328 | I35: Westminster Toyota | J35: TCI | K35: #N/A | L35: 45715.673 | M35: Offboarded | N35: #N/A
A36: 38 | B36: JTMAAAAA0PA028495 | C36: VC870J | D36: bZ4X | E36: 2023 | F36: LE | G36: Wind Chill Pearl | H36: 45328 | I36: Destination Toyota Burnaby | J36: TCI | K36: #N/A | L36: 45663.017 | M36: Sold | N36: #N/A
A37: 39 | B37: JTMABACA4PA045262 | C37: VC851J | D37: bZ4X | E37: 2023 | F37: XLE AWD | G37: Element Silver | H37: 45328 | I37: Destination Toyota Burnaby | J37: TCI | K37: #N/A | L37: 45669.663 | M37: Sold | N37: #N/A
A38: 40 | B38: JTMABACA5PA045139 | C38: VC873J | D38: bZ4X | E38: 2023 | F38: XLE AWD | G38: Wind Chill Pearl | H38: 45328 | I38: Destination Toyota Burnaby | J38: TCI | K38: #N/A | L38: 45687.632 | M38: Sold | N38: #N/A
A39: 41 | B39: JTMABACA2PA045471 | C39: VC863J | D39: bZ4X | E39: 2023 | F39: XLE AWD | G39: Element Silver | H39: 45328 | I39: Destination Toyota Burnaby | J39: TCCI | K39: #N/A | L39: 45663.672 | M39: Sold | N39: #N/A
A40: 42 | B40: JTMAAAAAXPA027970 | C40: VC865J | D40: bZ4X | E40: 2023 | F40: LE | G40: Wind Chill Pearl | H40: 45329 | I40: Destination Toyota Burnaby | J40: TCCI | K40: 89737 | L40: 46045.086 | M40: Onboarded | N40: inactive | O40: =+VLOOKUP(B40,'Dep TCCI'!$I$3:$AC$117,2,FALSE) -> 45611.71 | P40: =+VLOOKUP(B40,'Dep TCCI'!$I$3:$AC$117,20,FALSE) -> 18213.662 | Q40: =+O40-P40 -> 27398.048
A41: 43 | B41: JTMABACA1PA041363 | C41: VC856J | D41: bZ4X | E41: 2023 | F41: XLE AWD | G41: Nautical Blue | H41: 45328 | I41: Jim Pattison Toyota Surrey | J41: TCCI | K41: 47167 | L41: 45741.038 | M41: Offboarded | N41: inactive
A42: 67 | B42: JTMAAAAAXRA050104 | C42: WJ943C | D42: bZ4X | E42: 2024 | F42: LE | G42: Black | H42: 45635 | I42: Destination Toyota Burnaby | J42: TCI | K42: 40925 | L42: 46055.535 | M42: Onboarded | N42: active | O42: =+VLOOKUP(B42,'Dep TCCI'!$I$3:$AC$117,2,FALSE) -> 44782.095 | P42: =+VLOOKUP(B42,'Dep TCCI'!$I$3:$AC$117,20,FALSE) -> 11521.397 | Q42: =+O42-P42 -> 33260.698
A43: 68 | B43: JTMAAAAA8RA050148 | C43: WW605B | D43: bZ4X | E43: 2024 | F43: LE | G43: Black | H43: 45635 | I43: Destination Toyota Burnaby | J43: TCI | K43: 40256 | L43: 46021.625 | M43: Onboarded | N43: active | O43: =+VLOOKUP(B43,'Dep TCCI'!$I$3:$AC$117,2,FALSE) -> 44782.095 | P43: =+VLOOKUP(B43,'Dep TCCI'!$I$3:$AC$117,20,FALSE) -> 11521.397 | Q43: =+O43-P43 -> 33260.698
A44: 69 | B44: JTMAAAAA5RA050253 | C44: WW607B | D44: bZ4X | E44: 2024 | F44: LE | G44: Black | H44: 45635 | I44: Destination Toyota Burnaby | J44: TCI | K44: 47407 | L44: 46024.594 | M44: Onboarded | N44: active | O44: =+VLOOKUP(B44,'Dep TCCI'!$I$3:$AC$117,2,FALSE) -> 44782.095 | P44: =+VLOOKUP(B44,'Dep TCCI'!$I$3:$AC$117,20,FALSE) -> 11521.397 | Q44: =+O44-P44 -> 33260.698
A45: 70 | B45: JTMAAAAA5RA050334 | C45: WW604B | D45: bZ4X | E45: 2024 | F45: LE | G45: Black | H45: 45635 | I45: Destination Toyota Burnaby | J45: TCI | K45: 63761 | L45: 46052.77 | M45: Onboarded | N45: active | O45: =+VLOOKUP(B45,'Dep TCCI'!$I$3:$AC$117,2,FALSE) -> 44782.095 | P45: =+VLOOKUP(B45,'Dep TCCI'!$I$3:$AC$117,20,FALSE) -> 11521.397 | Q45: =+O45-P45 -> 33260.698
A46: 71 | B46: JTMAAAAA6RA050388 | C46: WW613B | D46: bZ4X | E46: 2024 | F46: LE | G46: Black | H46: 45635 | I46: Destination Toyota Burnaby | J46: TCI | K46: 54789 | L46: 46056.833 | M46: Onboarded | N46: inactive | O46: =+VLOOKUP(B46,'Dep TCCI'!$I$3:$AC$117,2,FALSE) -> 44782.095 | P46: =+VLOOKUP(B46,'Dep TCCI'!$I$3:$AC$117,20,FALSE) -> 11521.397 | Q46: =+O46-P46 -> 33260.698
A47: 72 | B47: JTMAAAAA5RA050706 | C47: WW572B | D47: bZ4X | E47: 2024 | F47: LE | G47: Nautical Blue | H47: 45635 | I47: Destination Toyota Burnaby | J47: TCI | K47: 60678 | L47: 46036.114 | M47: Onboarded | N47: active | O47: =+VLOOKUP(B47,'Dep TCCI'!$I$3:$AC$117,2,FALSE) -> 44782.095 | P47: =+VLOOKUP(B47,'Dep TCCI'!$I$3:$AC$117,20,FALSE) -> 11521.397 | Q47: =+O47-P47 -> 33260.698
A48: 73 | B48: JTMAAAAA8RA050716 | C48: WW614B | D48: bZ4X | E48: 2024 | F48: LE | G48: Nautical Blue | H48: 45635 | I48: Destination Toyota Burnaby | J48: TCI | K48: 41629 | L48: 46015.526 | M48: Onboarded | N48: active | O48: =+VLOOKUP(B48,'Dep TCCI'!$I$3:$AC$117,2,FALSE) -> 44782.095 | P48: =+VLOOKUP(B48,'Dep TCCI'!$I$3:$AC$117,20,FALSE) -> 11521.397 | Q48: =+O48-P48 -> 33260.698
A49: 74 | B49: JTMAAAAA1RA050816 | C49: WW564B | D49: bZ4X | E49: 2024 | F49: LE | G49: Nautical Blue | H49: 45635 | I49: Destination Toyota Burnaby | J49: TCI | K49: 29109 | L49: 46034.949 | M49: Onboarded | N49: inactive | O49: =+VLOOKUP(B49,'Dep TCCI'!$I$3:$AC$117,2,FALSE) -> 44782.095 | P49: =+VLOOKUP(B49,'Dep TCCI'!$I$3:$AC$117,20,FALSE) -> 11521.397 | Q49: =+O49-P49 -> 33260.698
A50: 75 | B50: JTMAAAAA0RA050998 | C50: WW573B | D50: bZ4X | E50: 2024 | F50: LE | G50: Nautical Blue | H50: 45636 | I50: Destination Toyota Burnaby | J50: TCI | K50: 46701 | L50: 46026.188 | M50: Onboarded | N50: active | O50: =+VLOOKUP(B50,'Dep TCCI'!$I$3:$AC$117,2,FALSE) -> 44782.095 | P50: =+VLOOKUP(B50,'Dep TCCI'!$I$3:$AC$117,20,FALSE) -> 11521.397 | Q50: =+O50-P50 -> 33260.698
A51: 76 | B51: JTMAAAAA4RA051104 | C51: WW554B | D51: bZ4X | E51: 2024 | F51: LE | G51: Nautical Blue | H51: 45635 | I51: Destination Toyota Burnaby | J51: TCI | K51: 58517 | L51: 46023.669 | M51: Onboarded | N51: active | O51: =+VLOOKUP(B51,'Dep TCCI'!$I$3:$AC$117,2,FALSE) -> 44782.095 | P51: =+VLOOKUP(B51,'Dep TCCI'!$I$3:$AC$117,20,FALSE) -> 11521.397 | Q51: =+O51-P51 -> 33260.698
A52: 77 | B52: JTMAAAAA5RA051242 | C52: WW574B | D52: bZ4X | E52: 2024 | F52: LE | G52: Nautical Blue | H52: 45635 | I52: Destination Toyota Burnaby | J52: TCI | K52: 42462 | L52: 46034.445 | M52: Onboarded | N52: active | O52: =+VLOOKUP(B52,'Dep TCCI'!$I$3:$AC$117,2,FALSE) -> 44782.095 | P52: =+VLOOKUP(B52,'Dep TCCI'!$I$3:$AC$117,20,FALSE) -> 11521.397 | Q52: =+O52-P52 -> 33260.698
A53: 78 | B53: JTMAAAAA3RA051224 | C53: WW584B | D53: bZ4X | E53: 2024 | F53: LE | G53: Nautical Blue | H53: 45635 | I53: Destination Toyota Burnaby | J53: TCI | K53: 55041 | L53: 46033.365 | M53: Onboarded | N53: active | O53: =+VLOOKUP(B53,'Dep TCCI'!$I$3:$AC$117,2,FALSE) -> 44782.095 | P53: =+VLOOKUP(B53,'Dep TCCI'!$I$3:$AC$117,20,FALSE) -> 11521.397 | Q53: =+O53-P53 -> 33260.698
... A84: 116 | B84: JTMABACA8SA096921 | C84: XA950L | D84: bZ4X | E84: 2025 | F84: LE | G84: Element Silver | H84: 45770 | I84: Westminster Toyota | J84: TCCI | K84: 59351 | L84: 46043.62 | M84: Onboarded | N84: active | O84: =+VLOOKUP(B84,'Dep TCCI'!$I$3:$AC$117,2,FALSE) -> 46452 | P84: =+VLOOKUP(B84,'Dep TCCI'!$I$3:$AC$117,20,FALSE) -> 12703.167 | Q84: =+O84-P84 -> 33748.833
